Workbook
Name \0: #N/A
Name \0_1: #N/A
Name \A: #N/A
Name \a.: #N/A
Name \a._1: #N/A
Name \A_1: #N/A
Name \B: #N/A
Name \b.: #N/A
Name \C: #REF!
Name \C: #REF!
Name \C: #REF!
Name \C: #REF!
Name \C: #REF!
Name \C: #REF!
Name \C_1: #N/A
Name \C_2: #N/A
Name \D: #REF!
Name \D: #REF!
Name \D: #REF!
Name \D: #REF!
Name \D: #REF!
Name \D: #REF!
Name \D_1: #N/A
Name \E: #N/A
Name \E_1: #N/A
Name \E1: #N/A
Name \E1_1: #N/A
Name \F: #N/A
Name \F_1: #N/A
Name \G: #N/A
Name \G_1: #N/A
Name \H: #N/A
Name \H_1: #N/A
Name \I: #REF!
Name \I_1: #N/A
Name \J: #N/A
Name \K: #N/A
Name \L: #N/A
Name \L_1: #N/A
Name \L_2: #N/A
Name \M: #N/A
Name \M_1: #N/A
Name \N: #REF!
Name \N_1: #N/A
Name \O: #N/A
Name \O_1: #N/A
Name \P: #N/A
Name \P_1: #N/A
Name \Q: #REF!
Name \Q_1: #N/A
Name \R: #REF!
Name \R_1: #N/A
Name \S: #N/A
Name \S_1: #N/A
Name \T: #REF!
Name \T_1: #N/A
Name \U: #N/A
Name \U_1: #N/A
Name \V: #N/A
Name \W: #N/A

Sheet BBM Maumere
C2: TABEL PROFITABILITY PROJECT | G2: KESIMPULAN ANALISIS KELAYAKAN PROJECT
C3: INFORMASI PROJECT | G3: =E6 -> Pekerjaan Pengadaan BBM TTC Maumere
C4: Nama Pelanggan | E4: Telkomsel | G4: =E4 -> Telkomsel
C5: Kategori Project | E5: PS | G5: REVENUE | I5: =IF(E37=D55,E37,"perhitungan salah, CEK KEMBALI CASH FLOW DAN BLOCK REVENUE STREAM") -> 44146500 | J5: =I5=E37 -> TRUE
C6: Nama Project | E6: Pekerjaan Pengadaan BBM TTC Maumere | G6: TOTAL BEBAN/CASH OUT | I6: =IF(E23=D58*-1,E23,"perhitungan salah, CEK KEMBALI CASH FLOW DAN BLOCKCOST STRUCTURE") -> 32973000 | J6: =I6=E23 -> TRUE
C7: Lokasi Project | E7: TTC Maumere | G7: GROSS MARGIN | H7: =I7/I5 -> 0.25310047 | I7: =I5-I6 -> 11173500 | J7: =I7=D67 -> TRUE
C8: Estimasi mulai pekerjaan (MM/YY) | E8: 46259 | G8: Total Pajak PPH | I8: =E41 -> 1169882.3 | J8: =I8=E41 -> TRUE
A9: =IF(E9="",0,1) -> 1 | C9: Durasi Project (bulan) | E9: 1 | G9: GROSS MARGIN + PPH | H9: =I9/I5 -> 0.22660047 | I9: =I7-I8 -> 10003618 | J9: =I9=D73 -> TRUE
A10: =IF(E10="",0,1) -> 1 | C10: Durasi Retensi (bulan) | E10: 0 | G10: Provisi | I10: =D76*-1 -> 7284.1725 | J10: =I10=E45 -> TRUE
C11: Pengawasan Konstruksi Sendiri / Menggunakan MK ? | E11: Sendiri ( by GSD ) | F11: *pilihan | G11: Bunga Pinjaman | I11: =D77*-1 -> 6610.3865 | J11: =I11=E46 -> TRUE
C12: Tipe Bagunan | D12: {=IF(E37<='[128]Tabel PUPR'!A15,'[128]Tabel PUPR'!B15,IF(E37<='[128]Tabel PUPR'!A16,'[128]Tabel PUPR'!B16,IF(E37<='[128]Tabel PUPR'!A17,'[128]Tabel PUPR'!B17,IF(E37<='[128]Tabel PUPR'!A18,'[128]Tabel PUPR'!B18,IF(E37<='[128]Tabel PUPR'!A19,'[128]Tabel PUPR'!B19,IF(E37<='[128]Tabel PUPR'!A20,'[128]Tabel PUPR'!B20,IF(E37<='[128]Tabel PUPR'!A21,'[128]Tabel PUPR'!B21,IF(E37<='[128]Tabel PUPR'!A22,'[128]Tabel PUPR'!B22,IF(E37<='[128]Tabel PUPR'!A23,'[128]Tabel PUPR'!B23,IF(E37<='[128]Tabel PUPR'!A24,'[128]Tabel PUPR'!B24,IF(E37<='[128]Tabel PUPR'!A25,k,k)))))))))))} -> a | E12: Sederhana ( < 2 lantai) | F12: *pilihan | G12: NET INCOME | H12: =I12/I5 -> 0.22628573 | I12: =I9-SUM(I10:I11) -> 9989723.2
C13: TOP Pembayaran Kepada Mitra | E13: setelah BAST | G13: Kredit PPN | I13: =-D72 -> 1229085
C14: TOP Pembayaran Pelanggan | E14: setelah BAST | G14: NET CASH FLOW | H14: =IF(I14>0,"Cashflow Positif","Cashflow Negatif") -> Cashflow Positif | I14: =I12-I13 -> 8760638.2 | K14: CATATAN:
C15: ASUMSI-ASUMSI | G15: CF selama kontrak | H15: =COUNTIF(E79:Q79,"<"&0) -> 0 | I15: =IF(H15>0,"Terdapat CF Negatif","All CF Positif") -> All CF Positif
A16: =IF(E10=[129]key!A3,1,0) -> 0 | C16: Suku Bunga per tahun | E16: 0.1089 | G16: KESIMPULAN | H16: =IF(H12>0%,IF(H15=0,IF(H12>10.89%,"Layak dengan Net Income sebesar",IF(I5>1000000000,IF(H12>10.89%,"Tidak Layak dengan Net income dibawah treshold ",IF(H12>0%,"Tidak Layak dengan Net income dibawah treshold","Tidak Layak dengan Net income dibawah treshold")),"Tidak Layak dengan Net income dibawah treshold")),"Tidak Layak dengan Net Income sebesar"),"Tidak Layak dengan Net income dibawah treshold") -> Layak dengan Net Income sebesar | K16: * JIKA TERDAPAT CF NEGATIF :
C17: Suku Bunga per bulan | E17: =E16/12 -> 0.009075 | H17: =H12 -> 0.22628573 | K17: 1. adjust nilai pinjaman hingga CF positif
C18: Pemodalan: Loan | E18: 1 | G18: REVENUE INCL PPN | H18: 11/12*12% | I18: =I5+D70 -> 49002615 | K18: 2. Adjust asumsi pembayaran mitra / customer, namun harus sesuai dengan
C19: Provisi | E19: 0.01 | G19: Notes lain-lain: | K19: kondisi aktual / konfirmasi dengan pihak OM
C20: PPN | E20: 0.12 | G20: =C24 -> Biaya Mitra Pelaksana (Exclude PPN) | I20: =E24 -> 32973000
C21: PPH pasal 23 | E21: 0.0265 | G21: =C31 -> BOP Project | I21: =E31 -> 0
C22: Periode Pinjaman (Bulan) | E22: =E9 -> 1 | G22: =C39 -> Management Fee GSD | I22: =E39 -> 11173500
C23: COST STRUCTURE / CASH OUT | E23: =SUM(E24:E31) -> 32973000
C24: Biaya Mitra Pelaksana (Exclude PPN) | E24: =COGS!H6 -> 32973000
C25: BEBAN LAINNYA | E25: 0
C26: Fee Fasilitas Jaminan | F26: * Minimal 500rb dengan catatan apabila contohnya: 1. Nilai Proyek 10M 2. Jangka waktu kerjasama adalah 3 bulan 3. Nilai Jaminan Dipersyaratkan 15% Maka Cost untuk fee: =(((0.5%/12)x3)x(15%x10M)
C27: Admin Fasilitas Jaminan | F27: * Apabila ada jaminan, biaya admin Rp 250.000,-
C28: Construction Assurance Risk ( CAR) | E28: 0
C29: Iuran Jasa Konstruksi | E29: 0
C30: Biaya Pengawasan | D30: =IF(E11='[128]Tabel PUPR'!D4,0%,VLOOKUP([128]Profitability!D12,'[128]Tabel PUPR'!B15:E25,IF([128]Profitability!E12='[128]Tabel PUPR'!A8,2,IF([128]Profitability!D12='[128]Tabel PUPR'!A9,3,4)))) -> 0 | E30: =D30*$E$24 -> 0 | F30: Berdasarkan PUPR : | G30: 0
C31: BOP Project | D31: =G31 -> 0 | E31: =D31*$E$24 -> 0 | F31: Berdasarkan PUPR : | G31: 0 | H31: *% bisa disesuaikan dengan asumsi sendiri pada kolom D31
C32: JAMINAN - JAMINAN | E32: =SUM(E33:E36) -> 0
C33: Jaminan Uang muka | D33: 0 | E33: =D33*$E$37 -> 0 | F33: * cek dan sesuaikan pengenaan % terhadap revenue / isi nilai manual pada kolom E
C34: Jaminan Penawaran | D34: 0 | E34: =D34*$E$37 -> 0 | F34: * cek dan sesuaikan pengenaan % terhadap revenue / isi nilai manual pada kolom E
C35: Jaminan Pelaksanaan | D35: 0 | E35: =D35*$E$37 -> 0 | F35: * cek dan sesuaikan pengenaan % terhadap revenue / isi nilai manual pada kolom E
C36: Jaminan Pemeliharaan | D36: 0 | E36: =D36*$E$37 -> 0 | F36: * cek dan sesuaikan pengenaan % terhadap revenue / isi nilai manual pada kolom E
C37: REVENUE STREAM / CASH IN | E37: =SUM(E38:E39) -> 44146500 | G37: 44146500
C38: Jasa Pelaksanaan konstruksi | E38: =E24 -> 32973000
C39: Management Fee GSD | D39: 0.33886816 | E39: =D39*SUM(E38) -> 11173500 | F39: *terhadap nilai mitra
C40: PERPAJAKAN
C41: PPh | E41: =D68*-1 -> 1169882.3
C42: PPn | E42: =D72*-1 -> 1229085
C43: PINJAMAN
C44: Besar Pinjaman | E44: =D74 -> 728417.25 | G44: Islam Fahri Rahman | I44: Hendroyono | K44: Abimanyu
C45: Biaya Provisi | E45: =-D76 -> 7284.1725 | G45: Mgr Product & Solution | I45: Mgr Planning & Delivery | K45: Mgr Marketing, Sales & Solution
C46: Bunga Pinjaman | E46: =D77*-1 -> 6610.3865
C48: CASHFLOW PROJECT
C49: Jangka Waktu | D49: Total | E49: 0 | F49: 1 | G49: 2 | H49: 3 | I49: 4 | J49: 5 | K49: 6 | L49: 7 | M49: 8 | N49: 9 | O49: 10 | P49: 11 | Q49: 12
A50: 1 | C50: Bulan | E50: =E8 -> 46259 | F50: =EDATE(E50,1) -> 46290 | G50: =EDATE(F50,1) -> 46320 | H50: =EDATE(G50,1) -> 46351 | I50: =EDATE(H50,1) -> 46381 | J50: =EDATE(I50,1) -> 46412 | K50: =EDATE(J50,1) -> 46443 | L50: =EDATE(K50,1) -> 46471 | M50: =EDATE(L50,1) -> 46502 | ... Q50: =EDATE(P50,1) -> 46624
A51: =A50+1 -> 2 | C51: TOP (progress)
C52: % PROGRESS PEKERJAAN | D52: =MAX(E52:Q52) -> 1 | E52: 0 | F52: 1 | G52: =IF(G49<=$E$9,100%/$E$9*G49,0) -> 0 | H52: =IF(H49<=$E$9,100%/$E$9*H49,0) -> 0 | I52: =IF(I49<=$E$9,100%/$E$9*I49,0) -> 0 | J52: =IF(J49<=$E$9,100%/$E$9*J49,0) -> 0 | K52: =IF(K49<=$E$9,100%/$E$9*K49,0) -> 0 | L52: =IF(L49<=$E$9,100%/$E$9*L49,0) -> 0 | M52: =IF(M49<=$E$9,100%/$E$9*M49,0) -> 0 | N52: =IF(N49<=$E$9,100%/$E$9*N49,0) -> 0 | ... Q52: =IF(Q49<=$E$9,100%/$E$9*Q49,0) -> 0
C53: % TERM OF PAYMENT PELANGGAN | D53: =SUM(E53:Q53) -> 1 | E53: 0 | F53: 1 | J53: 0 | K53: 0 | L53: 0 | M53: 0 | N53: 0 | O53: 0 | P53: 0 | Q53: 0 | R53: * sesuaikan dengan TOP
C54: % TERM OF PAYMENT KEPADA MITRA | D54: =SUM(E54:Q54) -> 1 | E54: =E53 -> 0 | F54: 1 | G54: =G53 -> 0 | H54: =H53 -> 0 | I54: =I53 -> 0 | J54: =J53 -> 0 | K54: =K53 -> 0 | L54: =L53 -> 0 | M54: =M53 -> 0 | N54: =N53 -> 0 | ... Q54: =Q53 -> 0
A55: =#REF!+1 -> #REF! | C55: =C37 -> REVENUE STREAM / CASH IN | D55: =SUM(E55:Q55) -> 44146500 | E55: =SUM(E56:E57) -> 0 | F55: =SUM(F56:F57) -> 44146500 | G55: =SUM(G56:G57) -> 0 | H55: =SUM(H56:H57) -> 0 | I55: =SUM(I56:I57) -> 0 | J55: =SUM(J56:J57) -> 0 | K55: =SUM(K56:K57) -> 0 | L55: =SUM(L56:L57) -> 0 | ... Q55: =SUM(Q56:Q57) -> 0
A56: =A55+1 -> #REF! | C56: Jasa Pelaksanaan konstruksi | D56: =SUM(E56:Q56) -> 32973000 | E56: 0 | F56: =F53*$E$38 -> 32973000 | G56: =G53*$E$38 -> 0 | H56: =H53*$E$38 -> 0 | I56: =I53*$E$38 -> 0 | J56: =J53*$E$38 -> 0 | K56: =K53*$E$38 -> 0 | L56: =L53*$E$38 -> 0 | M56: =M53*$E$38 -> 0 | ... Q56: =Q53*$E$38 -> 0
C57: =C39 -> Management Fee GSD | D57: =SUM(E57:Q57) -> 11173500 | E57: 0 | F57: =$E$39*F53 -> 11173500 | G57: =$E$39*G53 -> 0 | H57: =$E$39*H53 -> 0 | I57: =$E$39*I53 -> 0 | J57: =$E$39*J53 -> 0 | K57: =$E$39*K53 -> 0 | L57: =$E$39*L53 -> 0 | M57: =$E$39*M53 -> 0 | ... Q57: =$E$39*Q53 -> 0
A58: =#REF!+1 -> #REF! | C58: =C23 -> COST STRUCTURE / CASH OUT | D58: =SUM(E58:Q58) -> -32973000 | E58: =SUM(E59:E66) -> 0 | F58: =SUM(F59:F66) -> -32973000 | G58: =SUM(G59:G66) -> 0 | H58: =SUM(H59:H66) -> 0 | I58: =SUM(I59:I66) -> 0 | J58: =SUM(J59:J66) -> 0 | K58: =SUM(K59:K66) -> 0 | L58: =SUM(L59:L66) -> 0 | ... Q58: =SUM(Q59:Q66) -> 0
A59: =#REF!+1 -> #REF! | C59: =C24 -> Biaya Mitra Pelaksana (Exclude PPN) | D59: =SUM(E59:Q59) -> -32973000 | E59: =-E54*$E$24 -> 0 | F59: =-F54*$E$24 -> -32973000 | G59: =-G54*$E$24 -> 0 | H59: =-H54*$E$24 -> 0 | I59: =-I54*$E$24 -> 0 | J59: =-J54*$E$24 -> 0 | K59: =-K54*$E$24 -> 0 | L59: =-L54*$E$24 -> 0 | ... Q59: =-Q54*$E$24 -> 0
C60: =C25 -> BEBAN LAINNYA | D60: =SUM(E60:Q60) -> 0 | E60: 0 | F60: 0 | G60: 0 | H60: 0 | I60: 0 | J60: 0 | K60: 0 | L60: 0 | M60: 0 | N60: 0 | O60: 0 | P60: 0 | Q60: 0
C61: =C26 -> Fee Fasilitas Jaminan | D61: =SUM(E61:Q61) -> 0 | E61: =-E26 -> 0
C62: =C27 -> Admin Fasilitas Jaminan | D62: =SUM(E62:Q62) -> 0 | E62: =-E27 -> 0
C63: =C28 -> Construction Assurance Risk ( CAR) | D63: =SUM(E63:Q63) -> 0 | E63: 0 | F63: 0 | G63: 0 | H63: 0 | I63: 0 | J63: 0 | K63: 0 | L63: 0 | M63: 0 | N63: 0 | O63: 0 | P63: 0 | Q63: 0
C64: =C29 -> Iuran Jasa Konstruksi | D64: =SUM(E64:Q64) -> 0 | E64: 0 | F64: 0 | G64: 0 | H64: 0 | I64: 0 | J64: 0 | K64: 0 | L64: 0 | M64: 0 | N64: 0 | O64: 0 | P64: 0 | Q64: 0
C65: =C30 -> Biaya Pengawasan | D65: =SUM(E65:Q65) -> 0 | E65: 0 | F65: =-$E$30/($E$9) -> 0 | G65: =-$E$30/($E$9) -> 0 | H65: =-$E$30/($E$9) -> 0 | I65: =-$E$30/($E$9) -> 0 | J65: =-$E$30/($E$9) -> 0 | K65: =-$E$30/($E$9) -> 0 | L65: =-$E$30/($E$9) -> 0 | M65: =-$E$30/($E$9) -> 0 | ... Q65: =-$E$30/($E$9) -> 0
C66: =C31 -> BOP Project | D66: =SUM(E66:Q66) -> 0 | F66: =-$E$31/($E$9) -> 0
A67: =#REF!+1 -> #REF! | C67: GROSS MARGIN / EBIT | D67: =SUM(E67:Q67) -> 11173500 | E67: =E55+E58 -> 0 | F67: =F55+F58 -> 11173500 | G67: =G55+G58 -> 0 | H67: =H55+H58 -> 0 | I67: =I55+I58 -> 0 | J67: =J55+J58 -> 0 | K67: =K55+K58 -> 0 | L67: =L55+L58 -> 0 | ... Q67: =Q55+Q58 -> 0
A68: =A67+1 -> #REF! | C68: Pengurangan pph 23 | D68: =SUM(E68:Q68) -> -1169882.3 | E68: =-$E$21*E55 -> 0 | F68: =-$E$21*F55 -> -1169882.3 | G68: =-$E$21*G55 -> 0 | H68: =-$E$21*H55 -> 0 | I68: =-$E$21*I55 -> 0 | J68: =-$E$21*J55 -> 0 | K68: =-$E$21*K55 -> 0 | L68: =-$E$21*L55 -> 0 | ... Q68: =-$E$21*Q55 -> 0
C69: PPn yang harus dibayarkan | D69: =SUM(E69:Q69) -> 0
C70: PPn Keluaran | D70: =SUM(E70:Q70) -> 4856115 | E70: =11/12*12%*E55 -> 0 | F70: =11/12*12%*F55 -> 4856115 | G70: =11/12*12%*G55 -> 0 | H70: =11/12*12%*H55 -> 0 | I70: =11/12*12%*I55 -> 0 | J70: =11/12*12%*J55 -> 0 | K70: =11/12*12%*K55 -> 0 | L70: =11/12*12%*L55 -> 0 | ... Q70: =11/12*12%*Q55 -> 0
C71: PPn Masukan | D71: =SUM(E71:Q71) -> -3627030 | E71: =11/12*12%*E59 -> 0 | F71: =11/12*12%*F59 -> -3627030 | G71: =11/12*12%*G59 -> 0 | H71: =11/12*12%*H59 -> 0 | I71: =11/12*12%*I59 -> 0 | J71: =11/12*12%*J59 -> 0 | K71: =11/12*12%*K59 -> 0 | L71: =11/12*12%*L59 -> 0 | ... Q71: =11/12*12%*Q59 -> 0
C72: Kredit PPn | D72: =SUM(E72:Q72) -> -1229085 | E72: =-(E70+E71) -> 0 | F72: =-(F70+F71) -> -1229085 | G72: =-(G70+G71) -> 0 | H72: =-(H70+H71) -> 0 | I72: =-(I70+I71) -> 0 | J72: =-(J70+J71) -> 0 | K72: =-(K70+K71) -> 0 | L72: =-(L70+L71) -> 0 | ... Q72: =-(Q70+Q71) -> 0
A73: =#REF!+1 -> #REF! | C73: =G9 -> GROSS MARGIN + PPH | D73: =SUM(E73:Q73) -> 10003618 | E73: =SUM(E67:E68) -> 0 | F73: =SUM(F67:F68) -> 10003618 | G73: =SUM(G67:G68) -> 0 | H73: =SUM(H67:H68) -> 0 | I73: =SUM(I67:I68) -> 0 | J73: =SUM(J67:J68) -> 0 | K73: =SUM(K67:K68) -> 0 | L73: =SUM(L67:L68) -> 0 | ... Q73: =SUM(Q67:Q68) -> 0
C74: Penarikan Pinjaman | D74: =SUM(E74:Q74) -> 728417.25 | E74: =E82 -> 728417.25
C75: Pembayaran Pokok | D75: =SUM(E75:Q75) -> -728417.25 | F75: =-F103 -> -728417.25 | G75: =-G103 -> 0 | H75: =-H103 -> 0 | I75: =-I103 -> 0 | J75: =-J103 -> 0 | K75: =-K103 -> 0 | L75: =-L103 -> 0 | M75: =-M103 -> 0 | ... Q75: =-Q103 -> 0
A76: =A68+1 -> #REF! | C76: Biaya Provisi | D76: =SUM(E76:Q76) -> -7284.1725 | E76: =-E74*1% -> -7284.1725 | F76: =-F74*1% -> 0 | G76: =-G74*1% -> 0 | H76: =-H74*1% -> 0 | I76: =-I74*1% -> 0 | J76: =-J74*1% -> 0 | K76: =-K74*1% -> 0 | L76: =-L74*1% -> 0 | ... Q76: =-Q74*1% -> 0
A77: =A76+1 -> #REF! | C77: Beban Bunga | D77: =SUM(E77:Q77) -> -6610.3865 | F77: =-F104 -> -6610.3865 | G77: =-G104 -> 0 | H77: =-H104 -> 0 | I77: =-I104 -> 0 | J77: =-J104 -> 0 | K77: =-K104 -> 0 | L77: =-L104 -> 0 | M77: =-M104 -> 0 | ... Q77: =-Q104 -> 0
A78: =A77+1 -> #REF! | C78: CASH MARGIN | D78: =SUM(E78:Q78) -> 9989723.2 | E78: =E73+SUM(E74:E77) -> 721133.08 | F78: =F73+SUM(F74:F77) -> 9268590.1 | G78: =G73+SUM(G74:G77) -> 0 | H78: =H73+SUM(H74:H77) -> 0 | I78: =I73+SUM(I74:I77) -> 0 | J78: =J73+SUM(J74:J77) -> 0 | K78: =K73+SUM(K74:K77) -> 0 | L78: =L73+SUM(L74:L77) -> 0 | ... Q78: =Q73+SUM(Q74:Q77) -> 0
A79: =A78+1 -> #REF! | C79: CASH FLOW | E79: =E78 -> 721133.08 | F79: =F78+E79 -> 9989723.2
H80: =F79=D78 -> TRUE
F81: =1.65% -> 0.0165
E82: =F81*E37 -> 728417.25
D83: OS | F83: =E84 -> 728417.25 | H83: =G83-G84 -> 0 | I83: =H83-H84 -> 0 | J83: =I83-I84 -> 0 | K83: =J83-J84 -> 0 | L83: =K83-K84 -> 0 | M83: =L83-L84 -> 0 | N83: =M83-M84 -> 0 | O83: =N83-N84 -> 0 | ... Q83: =P83-P84 -> 0
D84: Pokok | E84: =SUM(F84:R84) -> 728417.25 | F84: =$E$82/1 -> 728417.25
D85: Bunga | F85: =($E$16/12)*1*F83 -> 6610.3865 | H85: =($E$16/12)*1*H83 -> 0 | I85: =($E$16/12)*1*I83 -> 0 | J85: =($E$16/12)*1*J83 -> 0 | K85: =($E$16/12)*1*K83 -> 0 | L85: =($E$16/12)*1*L83 -> 0 | M85: =($E$16/12)*1*M83 -> 0 | N85: =($E$16/12)*1*N83 -> 0 | O85: =($E$16/12)*1*O83 -> 0 | ... Q85: =($E$16/12)*1*Q83 -> 0
E87: 0
D88: OS | M88: =E89 -> 0 | N88: =M88-M89 -> 0 | O88: =N88-N89 -> 0 | P88: =O88-O89 -> 0 | Q88: =P88-P89 -> 0
D89: Pokok | E89: =SUM(F89:R89) -> 0 | M89: =E87/5 -> 0 | N89: =F87/5 -> 0 | O89: =G87/5 -> 0 | P89: =H87/5 -> 0 | Q89: =I87/5 -> 0
D90: Bunga | M90: =($E$16/12)*1*M88 -> 0 | N90: =($E$16/12)*1*N88 -> 0 | O90: =($E$16/12)*1*O88 -> 0 | P90: =($E$16/12)*1*P88 -> 0 | Q90: =($E$16/12)*1*Q88 -> 0
E92: 0
D93: OS | P93: =E92 -> 0 | Q93: =P93-P94 -> 0
D94: Pokok | E94: =SUM(F94:R94) -> 0 | P94: =$E$92/2 -> 0 | Q94: =$E$92/2 -> 0
D95: Bunga | P95: =($E$16/12)*1*P93 -> 0 | Q95: =($E$16/12)*1*Q93 -> 0
E97: 0
D98: OS | F98: =E99 -> 0 | G98: =F98-F99 -> 0 | H98: =G98-G99 -> 0 | I98: =H98-H99 -> 0 | J98: =I98-I99 -> 0 | K98: =J98-J99 -> 0 | L98: =K98-K99 -> 0 | M98: =L98-L99 -> 0 | N98: =M98-M99 -> 0 | ... Q98: =P98-P99 -> 0
D99: Pokok | E99: =SUM(F99:R99) -> 0 | F99: =$E$97/12 -> 0 | G99: =$E$97/12 -> 0 | H99: =$E$97/12 -> 0 | I99: =$E$97/12 -> 0 | J99: =$E$97/12 -> 0 | K99: =$E$97/12 -> 0 | L99: =$E$97/12 -> 0 | M99: =$E$97/12 -> 0 | ... Q99: =$E$97/12 -> 0
D100: Bunga | F100: =($E$16/12)*1*F98 -> 0 | G100: =($E$16/12)*1*G98 -> 0 | H100: =($E$16/12)*1*H98 -> 0 | I100: =($E$16/12)*1*I98 -> 0 | J100: =($E$16/12)*1*J98 -> 0 | K100: =($E$16/12)*1*K98 -> 0 | L100: =($E$16/12)*1*L98 -> 0 | M100: =($E$16/12)*1*M98 -> 0 | ... Q100: =($E$16/12)*1*Q98 -> 0
D102: TOTAL
D103: Pokok | E103: =SUM(F103:Q103) -> 728417.25 | F103: =F84+F89+F94+F99 -> 728417.25 | G103: =G84+G89+G94+G99 -> 0 | H103: =H84+H89+H94+H99 -> 0 | I103: =I84+I89+I94+I99 -> 0 | J103: =J84+J89+J94+J99 -> 0 | K103: =K84+K89+K94+K99 -> 0 | L103: =L84+L89+L94+L99 -> 0 | M103: =M84+M89+M94+M99 -> 0 | ... Q103: =Q84+Q89+Q94+Q99 -> 0
D104: Bunga | E104: =SUM(F104:Q104) -> 6610.3865 | F104: =F85+F90+F95+F100 -> 6610.3865 | G104: =G85+G90+G95+G100 -> 0 | H104: =H85+H90+H95+H100 -> 0 | I104: =I85+I90+I95+I100 -> 0 | J104: =J85+J90+J95+J100 -> 0 | K104: =K85+K90+K95+K100 -> 0 | L104: =L85+L90+L95+L100 -> 0 | M104: =M85+M90+M95+M100 -> 0 | ... Q104: =Q85+Q90+Q95+Q100 -> 0

Sheet BBM HRM
C2: TABEL PROFITABILITY PROJECT | G2: KESIMPULAN ANALISIS KELAYAKAN PROJECT
C3: INFORMASI PROJECT | G3: =E6 -> Pekerjaan Pengadaan BBM TTC HR Muh
C4: Nama Pelanggan | E4: Telkomsel | G4: =E4 -> Telkomsel
C5: Kategori Project | E5: PS | G5: REVENUE | I5: =IF(E37=D55,E37,"perhitungan salah, CEK KEMBALI CASH FLOW DAN BLOCK REVENUE STREAM") -> 29431000 | J5: =I5=E37 -> TRUE
C6: Nama Project | E6: Pekerjaan Pengadaan BBM TTC HR Muh | G6: TOTAL BEBAN/CASH OUT | I6: =IF(E23=D58*-1,E23,"perhitungan salah, CEK KEMBALI CASH FLOW DAN BLOCKCOST STRUCTURE") -> 22522523 | J6: =I6=E23 -> TRUE
C7: Lokasi Project | E7: TTC HR Muh | G7: GROSS MARGIN | H7: =I7/I5 -> 0.23473472 | I7: =I5-I6 -> 6908477.5 | J7: =I7=D67 -> TRUE
C8: Estimasi mulai pekerjaan (MM/YY) | E8: 46259 | G8: Total Pajak PPH | I8: =E41 -> 779921.5 | J8: =I8=E41 -> TRUE
A9: =IF(E9="",0,1) -> 1 | C9: Durasi Project (bulan) | E9: 1 | G9: GROSS MARGIN + PPH | H9: =I9/I5 -> 0.20823472 | I9: =I7-I8 -> 6128556
A10: =IF(E10="",0,1) -> 1 | C10: Durasi Retensi (bulan) | E10: 0 | G10: Provisi | I10: =D76*-1 -> 4856.115 | J10: =I10=E45 -> TRUE
C11: Pengawasan Konstruksi Sendiri / Menggunakan MK ? | E11: Sendiri ( by GSD ) | F11: *pilihan | G11: Bunga Pinjaman | I11: =D77*-1 -> 4406.9244 | J11: =I11=E46 -> TRUE
C12: Tipe Bagunan | D12: {=IF(E37<='[128]Tabel PUPR'!A15,'[128]Tabel PUPR'!B15,IF(E37<='[128]Tabel PUPR'!A16,'[128]Tabel PUPR'!B16,IF(E37<='[128]Tabel PUPR'!A17,'[128]Tabel PUPR'!B17,IF(E37<='[128]Tabel PUPR'!A18,'[128]Tabel PUPR'!B18,IF(E37<='[128]Tabel PUPR'!A19,'[128]Tabel PUPR'!B19,IF(E37<='[128]Tabel PUPR'!A20,'[128]Tabel PUPR'!B20,IF(E37<='[128]Tabel PUPR'!A21,'[128]Tabel PUPR'!B21,IF(E37<='[128]Tabel PUPR'!A22,'[128]Tabel PUPR'!B22,IF(E37<='[128]Tabel PUPR'!A23,'[128]Tabel PUPR'!B23,IF(E37<='[128]Tabel PUPR'!A24,'[128]Tabel PUPR'!B24,IF(E37<='[128]Tabel PUPR'!A25,k,k)))))))))))} -> a | E12: Sederhana ( < 2 lantai) | F12: *pilihan | G12: NET INCOME | H12: =I12/I5 -> 0.20791998 | I12: =I9-SUM(I10:I11) -> 6119292.9
C13: TOP Pembayaran Kepada Mitra | E13: setelah BAST | G13: Kredit PPN | I13: =-D72 -> 759932.52
C14: TOP Pembayaran Pelanggan | E14: setelah BAST | G14: NET CASH FLOW | H14: =IF(I14>0,"Cashflow Positif","Cashflow Negatif") -> Cashflow Positif | I14: =I12-I13 -> 5359360.4 | K14: CATATAN:
C15: ASUMSI-ASUMSI | G15: CF selama kontrak | H15: =COUNTIF(E79:Q79,"<"&0) -> 0 | I15: =IF(H15>0,"Terdapat CF Negatif","All CF Positif") -> All CF Positif
A16: =IF(E10=[129]key!A3,1,0) -> 0 | C16: Suku Bunga per tahun | E16: 0.1089 | G16: KESIMPULAN | H16: =IF(H12>0%,IF(H15=0,IF(H12>10.89%,"Layak dengan Net Income sebesar",IF(I5>1000000000,IF(H12>10.89%,"Tidak Layak dengan Net income dibawah treshold ",IF(H12>0%,"Tidak Layak dengan Net income dibawah treshold","Tidak Layak dengan Net income dibawah treshold")),"Tidak Layak dengan Net income dibawah treshold")),"Tidak Layak dengan Net Income sebesar"),"Tidak Layak dengan Net income dibawah treshold") -> Layak dengan Net Income sebesar | K16: * JIKA TERDAPAT CF NEGATIF :
C17: Suku Bunga per bulan | E17: =E16/12 -> 0.009075 | H17: =H12 -> 0.20791998 | K17: 1. adjust nilai pinjaman hingga CF positif
C18: Pemodalan: Loan | E18: 1 | G18: REVENUE INCL PPN | H18: 11/12*12% | I18: =I5+D70 -> 32668410 | K18: 2. Adjust asumsi pembayaran mitra / customer, namun harus sesuai dengan
C19: Provisi | E19: 0.01 | G19: Notes lain-lain: | K19: kondisi aktual / konfirmasi dengan pihak OM
C20: PPN | E20: 0.12 | G20: =C24 -> Biaya Mitra Pelaksana (Exclude PPN) | I20: =E24 -> 22522523
C21: PPH pasal 23 | E21: 0.0265 | G21: =C31 -> BOP Project | I21: =E31 -> 0
C22: Periode Pinjaman (Bulan) | E22: =E9 -> 1 | G22: =C39 -> Management Fee GSD | I22: =E39 -> 6908477.5
C23: COST STRUCTURE / CASH OUT | E23: =SUM(E24:E31) -> 22522523
C24: Biaya Mitra Pelaksana (Exclude PPN) | E24: =COGS!H7 -> 22522523
C25: BEBAN LAINNYA | E25: 0
C26: Fee Fasilitas Jaminan | F26: * Minimal 500rb dengan catatan apabila contohnya: 1. Nilai Proyek 10M 2. Jangka waktu kerjasama adalah 3 bulan 3. Nilai Jaminan Dipersyaratkan 15% Maka Cost untuk fee: =(((0.5%/12)x3)x(15%x10M)
C27: Admin Fasilitas Jaminan | F27: * Apabila ada jaminan, biaya admin Rp 250.000,-
C28: Construction Assurance Risk ( CAR) | E28: 0
C29: Iuran Jasa Konstruksi | E29: 0
C30: Biaya Pengawasan | D30: =IF(E11='[128]Tabel PUPR'!D4,0%,VLOOKUP([128]Profitability!D12,'[128]Tabel PUPR'!B15:E25,IF([128]Profitability!E12='[128]Tabel PUPR'!A8,2,IF([128]Profitability!D12='[128]Tabel PUPR'!A9,3,4)))) -> 0 | E30: =D30*$E$24 -> 0 | F30: Berdasarkan PUPR : | G30: 0
C31: BOP Project | D31: =G31 -> 0 | E31: =D31*$E$24 -> 0 | F31: Berdasarkan PUPR : | G31: 0 | H31: *% bisa disesuaikan dengan asumsi sendiri pada kolom D31
C32: JAMINAN - JAMINAN | E32: =SUM(E33:E36) -> 0
C33: Jaminan Uang muka | D33: 0 | E33: =D33*$E$37 -> 0 | F33: * cek dan sesuaikan pengenaan % terhadap revenue / isi nilai manual pada kolom E
C34: Jaminan Penawaran | D34: 0 | E34: =D34*$E$37 -> 0 | F34: * cek dan sesuaikan pengenaan % terhadap revenue / isi nilai manual pada kolom E
C35: Jaminan Pelaksanaan | D35: 0 | E35: =D35*$E$37 -> 0 | F35: * cek dan sesuaikan pengenaan % terhadap revenue / isi nilai manual pada kolom E
C36: Jaminan Pemeliharaan | D36: 0 | E36: =D36*$E$37 -> 0 | F36: * cek dan sesuaikan pengenaan % terhadap revenue / isi nilai manual pada kolom E
C37: REVENUE STREAM / CASH IN | E37: =SUM(E38:E39) -> 29431000 | G37: 29431000
C38: Jasa Pelaksanaan konstruksi | E38: =E24 -> 22522523
C39: Management Fee GSD | D39: 0.3067364 | E39: =D39*SUM(E38) -> 6908477.5 | F39: *terhadap nilai mitra
C40: PERPAJAKAN
C41: PPh | E41: =D68*-1 -> 779921.5
C42: PPn | E42: =D72*-1 -> 759932.52
C43: PINJAMAN
C44: Besar Pinjaman | E44: =D74 -> 485611.5 | G44: Islam Fahri Rahman | I44: Hendroyono | K44: Abimanyu
C45: Biaya Provisi | E45: =-D76 -> 4856.115 | G45: Mgr Product & Solution | I45: Mgr Planning & Delivery | K45: Mgr Marketing, Sales & Solution
C46: Bunga Pinjaman | E46: =D77*-1 -> 4406.9244
C48: CASHFLOW PROJECT
C49: Jangka Waktu | D49: Total | E49: 0 | F49: 1 | G49: 2 | H49: 3 | I49: 4 | J49: 5 | K49: 6 | L49: 7 | M49: 8 | N49: 9 | O49: 10 | P49: 11 | Q49: 12
A50: 1 | C50: Bulan | E50: =E8 -> 46259 | F50: =EDATE(E50,1) -> 46290 | G50: =EDATE(F50,1) -> 46320 | H50: =EDATE(G50,1) -> 46351 | I50: =EDATE(H50,1) -> 46381 | J50: =EDATE(I50,1) -> 46412 | K50: =EDATE(J50,1) -> 46443 | L50: =EDATE(K50,1) -> 46471 | M50: =EDATE(L50,1) -> 46502 | ... Q50: =EDATE(P50,1) -> 46624
A51: =A50+1 -> 2 | C51: TOP (progress)
C52: % PROGRESS PEKERJAAN | D52: =MAX(E52:Q52) -> 1 | E52: 0 | F52: 1 | G52: =IF(G49<=$E$9,100%/$E$9*G49,0) -> 0 | H52: =IF(H49<=$E$9,100%/$E$9*H49,0) -> 0 | I52: =IF(I49<=$E$9,100%/$E$9*I49,0) -> 0 | J52: =IF(J49<=$E$9,100%/$E$9*J49,0) -> 0 | K52: =IF(K49<=$E$9,100%/$E$9*K49,0) -> 0 | L52: =IF(L49<=$E$9,100%/$E$9*L49,0) -> 0 | M52: =IF(M49<=$E$9,100%/$E$9*M49,0) -> 0 | N52: =IF(N49<=$E$9,100%/$E$9*N49,0) -> 0 | ... Q52: =IF(Q49<=$E$9,100%/$E$9*Q49,0) -> 0
C53: % TERM OF PAYMENT PELANGGAN | D53: =SUM(E53:Q53) -> 1 | E53: 0 | F53: 1 | J53: 0 | K53: 0 | L53: 0 | M53: 0 | N53: 0 | O53: 0 | P53: 0 | Q53: 0 | R53: * sesuaikan dengan TOP
C54: % TERM OF PAYMENT KEPADA MITRA | D54: =SUM(E54:Q54) -> 1 | E54: =E53 -> 0 | F54: 1 | G54: =G53 -> 0 | H54: =H53 -> 0 | I54: =I53 -> 0 | J54: =J53 -> 0 | K54: =K53 -> 0 | L54: =L53 -> 0 | M54: =M53 -> 0 | N54: =N53 -> 0 | ... Q54: =Q53 -> 0
A55: =#REF!+1 -> #REF! | C55: =C37 -> REVENUE STREAM / CASH IN | D55: =SUM(E55:Q55) -> 29431000 | E55: =SUM(E56:E57) -> 0 | F55: =SUM(F56:F57) -> 29431000 | G55: =SUM(G56:G57) -> 0 | H55: =SUM(H56:H57) -> 0 | I55: =SUM(I56:I57) -> 0 | J55: =SUM(J56:J57) -> 0 | K55: =SUM(K56:K57) -> 0 | L55: =SUM(L56:L57) -> 0 | ... Q55: =SUM(Q56:Q57) -> 0
A56: =A55+1 -> #REF! | C56: Jasa Pelaksanaan konstruksi | D56: =SUM(E56:Q56) -> 22522523 | E56: 0 | F56: =F53*$E$38 -> 22522523 | G56: =G53*$E$38 -> 0 | H56: =H53*$E$38 -> 0 | I56: =I53*$E$38 -> 0 | J56: =J53*$E$38 -> 0 | K56: =K53*$E$38 -> 0 | L56: =L53*$E$38 -> 0 | M56: =M53*$E$38 -> 0 | ... Q56: =Q53*$E$38 -> 0
C57: =C39 -> Management Fee GSD | D57: =SUM(E57:Q57) -> 6908477.5 | E57: 0 | F57: =$E$39*F53 -> 6908477.5 | G57: =$E$39*G53 -> 0 | H57: =$E$39*H53 -> 0 | I57: =$E$39*I53 -> 0 | J57: =$E$39*J53 -> 0 | K57: =$E$39*K53 -> 0 | L57: =$E$39*L53 -> 0 | M57: =$E$39*M53 -> 0 | ... Q57: =$E$39*Q53 -> 0
A58: =#REF!+1 -> #REF! | C58: =C23 -> COST STRUCTURE / CASH OUT | D58: =SUM(E58:Q58) -> -22522523 | E58: =SUM(E59:E66) -> 0 | F58: =SUM(F59:F66) -> -22522523 | G58: =SUM(G59:G66) -> 0 | H58: =SUM(H59:H66) -> 0 | I58: =SUM(I59:I66) -> 0 | J58: =SUM(J59:J66) -> 0 | K58: =SUM(K59:K66) -> 0 | L58: =SUM(L59:L66) -> 0 | ... Q58: =SUM(Q59:Q66) -> 0
A59: =#REF!+1 -> #REF! | C59: =C24 -> Biaya Mitra Pelaksana (Exclude PPN) | D59: =SUM(E59:Q59) -> -22522523 | E59: =-E54*$E$24 -> 0 | F59: =-F54*$E$24 -> -22522523 | G59: =-G54*$E$24 -> 0 | H59: =-H54*$E$24 -> 0 | I59: =-I54*$E$24 -> 0 | J59: =-J54*$E$24 -> 0 | K59: =-K54*$E$24 -> 0 | L59: =-L54*$E$24 -> 0 | ... Q59: =-Q54*$E$24 -> 0
C60: =C25 -> BEBAN LAINNYA | D60: =SUM(E60:Q60) -> 0 | E60: 0 | F60: 0 | G60: 0 | H60: 0 | I60: 0 | J60: 0 | K60: 0 | L60: 0 | M60: 0 | N60: 0 | O60: 0 | P60: 0 | Q60: 0
C61: =C26 -> Fee Fasilitas Jaminan | D61: =SUM(E61:Q61) -> 0 | E61: =-E26 -> 0
C62: =C27 -> Admin Fasilitas Jaminan | D62: =SUM(E62:Q62) -> 0 | E62: =-E27 -> 0
C63: =C28 -> Construction Assurance Risk ( CAR) | D63: =SUM(E63:Q63) -> 0 | E63: 0 | F63: 0 | G63: 0 | H63: 0 | I63: 0 | J63: 0 | K63: 0 | L63: 0 | M63: 0 | N63: 0 | O63: 0 | P63: 0 | Q63: 0
C64: =C29 -> Iuran Jasa Konstruksi | D64: =SUM(E64:Q64) -> 0 | E64: 0 | F64: 0 | G64: 0 | H64: 0 | I64: 0 | J64: 0 | K64: 0 | L64: 0 | M64: 0 | N64: 0 | O64: 0 | P64: 0 | Q64: 0
C65: =C30 -> Biaya Pengawasan | D65: =SUM(E65:Q65) -> 0 | E65: 0 | F65: =-$E$30/($E$9) -> 0 | G65: =-$E$30/($E$9) -> 0 | H65: =-$E$30/($E$9) -> 0 | I65: =-$E$30/($E$9) -> 0 | J65: =-$E$30/($E$9) -> 0 | K65: =-$E$30/($E$9) -> 0 | L65: =-$E$30/($E$9) -> 0 | M65: =-$E$30/($E$9) -> 0 | ... Q65: =-$E$30/($E$9) -> 0
C66: =C31 -> BOP Project | D66: =SUM(E66:Q66) -> 0 | F66: =-$E$31/($E$9) -> 0
A67: =#REF!+1 -> #REF! | C67: GROSS MARGIN / EBIT | D67: =SUM(E67:Q67) -> 6908477.5 | E67: =E55+E58 -> 0 | F67: =F55+F58 -> 6908477.5 | G67: =G55+G58 -> 0 | H67: =H55+H58 -> 0 | I67: =I55+I58 -> 0 | J67: =J55+J58 -> 0 | K67: =K55+K58 -> 0 | L67: =L55+L58 -> 0 | ... Q67: =Q55+Q58 -> 0
A68: =A67+1 -> #REF! | C68: Pengurangan pph 23 | D68: =SUM(E68:Q68) -> -779921.5 | E68: =-$E$21*E55 -> 0 | F68: =-$E$21*F55 -> -779921.5 | G68: =-$E$21*G55 -> 0 | H68: =-$E$21*H55 -> 0 | I68: =-$E$21*I55 -> 0 | J68: =-$E$21*J55 -> 0 | K68: =-$E$21*K55 -> 0 | L68: =-$E$21*L55 -> 0 | ... Q68: =-$E$21*Q55 -> 0
C69: PPn yang harus dibayarkan | D69: =SUM(E69:Q69) -> 0
C70: PPn Keluaran | D70: =SUM(E70:Q70) -> 3237410 | E70: =11/12*12%*E55 -> 0 | F70: =11/12*12%*F55 -> 3237410 | G70: =11/12*12%*G55 -> 0 | H70: =11/12*12%*H55 -> 0 | I70: =11/12*12%*I55 -> 0 | J70: =11/12*12%*J55 -> 0 | K70: =11/12*12%*K55 -> 0 | L70: =11/12*12%*L55 -> 0 | ... Q70: =11/12*12%*Q55 -> 0
C71: PPn Masukan | D71: =SUM(E71:Q71) -> -2477477.5 | E71: =11/12*12%*E59 -> 0 | F71: =11/12*12%*F59 -> -2477477.5 | G71: =11/12*12%*G59 -> 0 | H71: =11/12*12%*H59 -> 0 | I71: =11/12*12%*I59 -> 0 | J71: =11/12*12%*J59 -> 0 | K71: =11/12*12%*K59 -> 0 | L71: =11/12*12%*L59 -> 0 | ... Q71: =11/12*12%*Q59 -> 0
C72: Kredit PPn | D72: =SUM(E72:Q72) -> -759932.52 | E72: =-(E70+E71) -> 0 | F72: =-(F70+F71) -> -759932.52 | G72: =-(G70+G71) -> 0 | H72: =-(H70+H71) -> 0 | I72: =-(I70+I71) -> 0 | J72: =-(J70+J71) -> 0 | K72: =-(K70+K71) -> 0 | L72: =-(L70+L71) -> 0 | ... Q72: =-(Q70+Q71) -> 0
A73: =#REF!+1 -> #REF! | C73: =G9 -> GROSS MARGIN + PPH | D73: =SUM(E73:Q73) -> 6128556 | E73: =SUM(E67:E68) -> 0 | F73: =SUM(F67:F68) -> 6128556 | G73: =SUM(G67:G68) -> 0 | H73: =SUM(H67:H68) -> 0 | I73: =SUM(I67:I68) -> 0 | J73: =SUM(J67:J68) -> 0 | K73: =SUM(K67:K68) -> 0 | L73: =SUM(L67:L68) -> 0 | ... Q73: =SUM(Q67:Q68) -> 0
C74: Penarikan Pinjaman | D74: =SUM(E74:Q74) -> 485611.5 | E74: =E82 -> 485611.5
C75: Pembayaran Pokok | D75: =SUM(E75:Q75) -> -485611.5 | F75: =-F103 -> -485611.5 | G75: =-G103 -> 0 | H75: =-H103 -> 0 | I75: =-I103 -> 0 | J75: =-J103 -> 0 | K75: =-K103 -> 0 | L75: =-L103 -> 0 | M75: =-M103 -> 0 | ... Q75: =-Q103 -> 0
A76: =A68+1 -> #REF! | C76: Biaya Provisi | D76: =SUM(E76:Q76) -> -4856.115 | E76: =-E74*1% -> -4856.115 | F76: =-F74*1% -> 0 | G76: =-G74*1% -> 0 | H76: =-H74*1% -> 0 | I76: =-I74*1% -> 0 | J76: =-J74*1% -> 0 | K76: =-K74*1% -> 0 | L76: =-L74*1% -> 0 | ... Q76: =-Q74*1% -> 0
A77: =A76+1 -> #REF! | C77: Beban Bunga | D77: =SUM(E77:Q77) -> -4406.9244 | F77: =-F104 -> -4406.9244 | G77: =-G104 -> 0 | H77: =-H104 -> 0 | I77: =-I104 -> 0 | J77: =-J104 -> 0 | K77: =-K104 -> 0 | L77: =-L104 -> 0 | M77: =-M104 -> 0 | ... Q77: =-Q104 -> 0
A78: =A77+1 -> #REF! | C78: CASH MARGIN | D78: =SUM(E78:Q78) -> 6119292.9 | E78: =E73+SUM(E74:E77) -> 480755.39 | F78: =F73+SUM(F74:F77) -> 5638537.6 | G78: =G73+SUM(G74:G77) -> 0 | H78: =H73+SUM(H74:H77) -> 0 | I78: =I73+SUM(I74:I77) -> 0 | J78: =J73+SUM(J74:J77) -> 0 | K78: =K73+SUM(K74:K77) -> 0 | L78: =L73+SUM(L74:L77) -> 0 | ... Q78: =Q73+SUM(Q74:Q77) -> 0
A79: =A78+1 -> #REF! | C79: CASH FLOW | E79: =E78 -> 480755.39 | F79: =F78+E79 -> 6119292.9
H80: =F79=D78 -> TRUE
F81: =1.65% -> 0.0165
E82: =F81*E37 -> 485611.5
D83: OS | F83: =E84 -> 485611.5 | H83: =G83-G84 -> 0 | I83: =H83-H84 -> 0 | J83: =I83-I84 -> 0 | K83: =J83-J84 -> 0 | L83: =K83-K84 -> 0 | M83: =L83-L84 -> 0 | N83: =M83-M84 -> 0 | O83: =N83-N84 -> 0 | ... Q83: =P83-P84 -> 0
D84: Pokok | E84: =SUM(F84:R84) -> 485611.5 | F84: =$E$82/1 -> 485611.5
D85: Bunga | F85: =($E$16/12)*1*F83 -> 4406.9244 | H85: =($E$16/12)*1*H83 -> 0 | I85: =($E$16/12)*1*I83 -> 0 | J85: =($E$16/12)*1*J83 -> 0 | K85: =($E$16/12)*1*K83 -> 0 | L85: =($E$16/12)*1*L83 -> 0 | M85: =($E$16/12)*1*M83 -> 0 | N85: =($E$16/12)*1*N83 -> 0 | O85: =($E$16/12)*1*O83 -> 0 | ... Q85: =($E$16/12)*1*Q83 -> 0
E87: 0
D88: OS | M88: =E89 -> 0 | N88: =M88-M89 -> 0 | O88: =N88-N89 -> 0 | P88: =O88-O89 -> 0 | Q88: =P88-P89 -> 0
D89: Pokok | E89: =SUM(F89:R89) -> 0 | M89: =E87/5 -> 0 | N89: =F87/5 -> 0 | O89: =G87/5 -> 0 | P89: =H87/5 -> 0 | Q89: =I87/5 -> 0
D90: Bunga | M90: =($E$16/12)*1*M88 -> 0 | N90: =($E$16/12)*1*N88 -> 0 | O90: =($E$16/12)*1*O88 -> 0 | P90: =($E$16/12)*1*P88 -> 0 | Q90: =($E$16/12)*1*Q88 -> 0
E92: 0
D93: OS | P93: =E92 -> 0 | Q93: =P93-P94 -> 0
D94: Pokok | E94: =SUM(F94:R94) -> 0 | P94: =$E$92/2 -> 0 | Q94: =$E$92/2 -> 0
D95: Bunga | P95: =($E$16/12)*1*P93 -> 0 | Q95: =($E$16/12)*1*Q93 -> 0
E97: 0
D98: OS | F98: =E99 -> 0 | G98: =F98-F99 -> 0 | H98: =G98-G99 -> 0 | I98: =H98-H99 -> 0 | J98: =I98-I99 -> 0 | K98: =J98-J99 -> 0 | L98: =K98-K99 -> 0 | M98: =L98-L99 -> 0 | N98: =M98-M99 -> 0 | ... Q98: =P98-P99 -> 0
D99: Pokok | E99: =SUM(F99:R99) -> 0 | F99: =$E$97/12 -> 0 | G99: =$E$97/12 -> 0 | H99: =$E$97/12 -> 0 | I99: =$E$97/12 -> 0 | J99: =$E$97/12 -> 0 | K99: =$E$97/12 -> 0 | L99: =$E$97/12 -> 0 | M99: =$E$97/12 -> 0 | ... Q99: =$E$97/12 -> 0
D100: Bunga | F100: =($E$16/12)*1*F98 -> 0 | G100: =($E$16/12)*1*G98 -> 0 | H100: =($E$16/12)*1*H98 -> 0 | I100: =($E$16/12)*1*I98 -> 0 | J100: =($E$16/12)*1*J98 -> 0 | K100: =($E$16/12)*1*K98 -> 0 | L100: =($E$16/12)*1*L98 -> 0 | M100: =($E$16/12)*1*M98 -> 0 | ... Q100: =($E$16/12)*1*Q98 -> 0
D102: TOTAL
D103: Pokok | E103: =SUM(F103:Q103) -> 485611.5 | F103: =F84+F89+F94+F99 -> 485611.5 | G103: =G84+G89+G94+G99 -> 0 | H103: =H84+H89+H94+H99 -> 0 | I103: =I84+I89+I94+I99 -> 0 | J103: =J84+J89+J94+J99 -> 0 | K103: =K84+K89+K94+K99 -> 0 | L103: =L84+L89+L94+L99 -> 0 | M103: =M84+M89+M94+M99 -> 0 | ... Q103: =Q84+Q89+Q94+Q99 -> 0
D104: Bunga | E104: =SUM(F104:Q104) -> 4406.9244 | F104: =F85+F90+F95+F100 -> 4406.9244 | G104: =G85+G90+G95+G100 -> 0 | H104: =H85+H90+H95+H100 -> 0 | I104: =I85+I90+I95+I100 -> 0 | J104: =J85+J90+J95+J100 -> 0 | K104: =K85+K90+K95+K100 -> 0 | L104: =L85+L90+L95+L100 -> 0 | M104: =M85+M90+M95+M100 -> 0 | ... Q104: =Q85+Q90+Q95+Q100 -> 0

Sheet BBM Gayungan
C2: TABEL PROFITABILITY PROJECT | G2: KESIMPULAN ANALISIS KELAYAKAN PROJECT
C3: INFORMASI PROJECT | G3: =E6 -> Pekerjaan Pengadaan BBM TTC Gayungan
C4: Nama Pelanggan | E4: Telkomsel | G4: =E4 -> Telkomsel
C5: Kategori Project | E5: PS | G5: REVENUE | I5: =IF(E37=D55,E37,"perhitungan salah, CEK KEMBALI CASH FLOW DAN BLOCK REVENUE STREAM") -> 1.17724e+08 | J5: =I5=E37 -> TRUE
C6: Nama Project | E6: Pekerjaan Pengadaan BBM TTC Gayungan | G6: TOTAL BEBAN/CASH OUT | I6: =IF(E23=D58*-1,E23,"perhitungan salah, CEK KEMBALI CASH FLOW DAN BLOCKCOST STRUCTURE") -> 90090090 | J6: =I6=E23 -> TRUE
C7: Lokasi Project | E7: TTC Gayungan | G7: GROSS MARGIN | H7: =I7/I5 -> 0.23473472 | I7: =I5-I6 -> 27633910 | J7: =I7=D67 -> TRUE
C8: Estimasi mulai pekerjaan (MM/YY) | E8: 46259 | G8: Total Pajak PPH | I8: =E41 -> 3119686 | J8: =I8=E41 -> TRUE
A9: =IF(E9="",0,1) -> 1 | C9: Durasi Project (bulan) | E9: 1 | G9: GROSS MARGIN + PPH | H9: =I9/I5 -> 0.20823472 | I9: =I7-I8 -> 24514224
A10: =IF(E10="",0,1) -> 1 | C10: Durasi Retensi (bulan) | E10: 0 | G10: Provisi | I10: =D76*-1 -> 19424.46 | J10: =I10=E45 -> TRUE
C11: Pengawasan Konstruksi Sendiri / Menggunakan MK ? | E11: Sendiri ( by GSD ) | F11: *pilihan | G11: Bunga Pinjaman | I11: =D77*-1 -> 17627.697 | J11: =I11=E46 -> TRUE
C12: Tipe Bagunan | D12: {=IF(E37<='[128]Tabel PUPR'!A15,'[128]Tabel PUPR'!B15,IF(E37<='[128]Tabel PUPR'!A16,'[128]Tabel PUPR'!B16,IF(E37<='[128]Tabel PUPR'!A17,'[128]Tabel PUPR'!B17,IF(E37<='[128]Tabel PUPR'!A18,'[128]Tabel PUPR'!B18,IF(E37<='[128]Tabel PUPR'!A19,'[128]Tabel PUPR'!B19,IF(E37<='[128]Tabel PUPR'!A20,'[128]Tabel PUPR'!B20,IF(E37<='[128]Tabel PUPR'!A21,'[128]Tabel PUPR'!B21,IF(E37<='[128]Tabel PUPR'!A22,'[128]Tabel PUPR'!B22,IF(E37<='[128]Tabel PUPR'!A23,'[128]Tabel PUPR'!B23,IF(E37<='[128]Tabel PUPR'!A24,'[128]Tabel PUPR'!B24,IF(E37<='[128]Tabel PUPR'!A25,k,k)))))))))))} -> a | E12: Sederhana ( < 2 lantai) | F12: *pilihan | G12: NET INCOME | H12: =I12/I5 -> 0.20791998 | I12: =I9-SUM(I10:I11) -> 24477172
C13: TOP Pembayaran Kepada Mitra | E13: setelah BAST | G13: Kredit PPN | I13: =-D72 -> 3039730.1
C14: TOP Pembayaran Pelanggan | E14: setelah BAST | G14: NET CASH FLOW | H14: =IF(I14>0,"Cashflow Positif","Cashflow Negatif") -> Cashflow Positif | I14: =I12-I13 -> 21437442 | K14: CATATAN:
C15: ASUMSI-ASUMSI | G15: CF selama kontrak | H15: =COUNTIF(E79:Q79,"<"&0) -> 0 | I15: =IF(H15>0,"Terdapat CF Negatif","All CF Positif") -> All CF Positif
A16: =IF(E10=[129]key!A3,1,0) -> 0 | C16: Suku Bunga per tahun | E16: 0.1089 | G16: KESIMPULAN | H16: =IF(H12>0%,IF(H15=0,IF(H12>10.89%,"Layak dengan Net Income sebesar",IF(I5>1000000000,IF(H12>10.89%,"Tidak Layak dengan Net income dibawah treshold ",IF(H12>0%,"Tidak Layak dengan Net income dibawah treshold","Tidak Layak dengan Net income dibawah treshold")),"Tidak Layak dengan Net income dibawah treshold")),"Tidak Layak dengan Net Income sebesar"),"Tidak Layak dengan Net income dibawah treshold") -> Layak dengan Net Income sebesar | K16: * JIKA TERDAPAT CF NEGATIF :
C17: Suku Bunga per bulan | E17: =E16/12 -> 0.009075 | H17: =H12 -> 0.20791998 | K17: 1. adjust nilai pinjaman hingga CF positif
C18: Pemodalan: Loan | E18: 1 | G18: REVENUE INCL PPN | H18: 11/12*12% | I18: =I5+D70 -> 1.3067364e+08 | K18: 2. Adjust asumsi pembayaran mitra / customer, namun harus sesuai dengan
C19: Provisi | E19: 0.01 | G19: Notes lain-lain: | K19: kondisi aktual / konfirmasi dengan pihak OM
C20: PPN | E20: 0.12 | G20: =C24 -> Biaya Mitra Pelaksana (Exclude PPN) | I20: =E24 -> 90090090
C21: PPH pasal 23 | E21: 0.0265 | G21: =C31 -> BOP Project | I21: =E31 -> 0
C22: Periode Pinjaman (Bulan) | E22: =E9 -> 1 | G22: =C39 -> Management Fee GSD | I22: =E39 -> 27633910
C23: COST STRUCTURE / CASH OUT | E23: =SUM(E24:E31) -> 90090090
C24: Biaya Mitra Pelaksana (Exclude PPN) | E24: =COGS!H8 -> 90090090
C25: BEBAN LAINNYA | E25: 0
C26: Fee Fasilitas Jaminan | F26: * Minimal 500rb dengan catatan apabila contohnya: 1. Nilai Proyek 10M 2. Jangka waktu kerjasama adalah 3 bulan 3. Nilai Jaminan Dipersyaratkan 15% Maka Cost untuk fee: =(((0.5%/12)x3)x(15%x10M)
C27: Admin Fasilitas Jaminan | F27: * Apabila ada jaminan, biaya admin Rp 250.000,-
C28: Construction Assurance Risk ( CAR) | E28: 0
C29: Iuran Jasa Konstruksi | E29: 0
C30: Biaya Pengawasan | D30: =IF(E11='[128]Tabel PUPR'!D4,0%,VLOOKUP([128]Profitability!D12,'[128]Tabel PUPR'!B15:E25,IF([128]Profitability!E12='[128]Tabel PUPR'!A8,2,IF([128]Profitability!D12='[128]Tabel PUPR'!A9,3,4)))) -> 0 | E30: =D30*$E$24 -> 0 | F30: Berdasarkan PUPR : | G30: 0
C31: BOP Project | D31: =G31 -> 0 | E31: =D31*$E$24 -> 0 | F31: Berdasarkan PUPR : | G31: 0 | H31: *% bisa disesuaikan dengan asumsi sendiri pada kolom D31
C32: JAMINAN - JAMINAN | E32: =SUM(E33:E36) -> 0
C33: Jaminan Uang muka | D33: 0 | E33: =D33*$E$37 -> 0 | F33: * cek dan sesuaikan pengenaan % terhadap revenue / isi nilai manual pada kolom E
C34: Jaminan Penawaran | D34: 0 | E34: =D34*$E$37 -> 0 | F34: * cek dan sesuaikan pengenaan % terhadap revenue / isi nilai manual pada kolom E
C35: Jaminan Pelaksanaan | D35: 0 | E35: =D35*$E$37 -> 0 | F35: * cek dan sesuaikan pengenaan % terhadap revenue / isi nilai manual pada kolom E
C36: Jaminan Pemeliharaan | D36: 0 | E36: =D36*$E$37 -> 0 | F36: * cek dan sesuaikan pengenaan % terhadap revenue / isi nilai manual pada kolom E
C37: REVENUE STREAM / CASH IN | E37: =SUM(E38:E39) -> 1.17724e+08 | G37: 117724000
C38: Jasa Pelaksanaan konstruksi | E38: =E24 -> 90090090
C39: Management Fee GSD | D39: 0.3067364 | E39: =D39*SUM(E38) -> 27633910 | F39: *terhadap nilai mitra
C40: PERPAJAKAN
C41: PPh | E41: =D68*-1 -> 3119686
C42: PPn | E42: =D72*-1 -> 3039730.1
C43: PINJAMAN
C44: Besar Pinjaman | E44: =D74 -> 1942446 | G44: Islam Fahri Rahman | I44: Hendroyono | K44: Abimanyu
C45: Biaya Provisi | E45: =-D76 -> 19424.46 | G45: Mgr Product & Solution | I45: Mgr Planning & Delivery | K45: Mgr Marketing, Sales & Solution
C46: Bunga Pinjaman | E46: =D77*-1 -> 17627.697
C48: CASHFLOW PROJECT
C49: Jangka Waktu | D49: Total | E49: 0 | F49: 1 | G49: 2 | H49: 3 | I49: 4 | J49: 5 | K49: 6 | L49: 7 | M49: 8 | N49: 9 | O49: 10 | P49: 11 | Q49: 12
A50: 1 | C50: Bulan | E50: =E8 -> 46259 | F50: =EDATE(E50,1) -> 46290 | G50: =EDATE(F50,1) -> 46320 | H50: =EDATE(G50,1) -> 46351 | I50: =EDATE(H50,1) -> 46381 | J50: =EDATE(I50,1) -> 46412 | K50: =EDATE(J50,1) -> 46443 | L50: =EDATE(K50,1) -> 46471 | M50: =EDATE(L50,1) -> 46502 | ... Q50: =EDATE(P50,1) -> 46624
A51: =A50+1 -> 2 | C51: TOP (progress)
C52: % PROGRESS PEKERJAAN | D52: =MAX(E52:Q52) -> 1 | E52: 0 | F52: 1 | G52: =IF(G49<=$E$9,100%/$E$9*G49,0) -> 0 | H52: =IF(H49<=$E$9,100%/$E$9*H49,0) -> 0 | I52: =IF(I49<=$E$9,100%/$E$9*I49,0) -> 0 | J52: =IF(J49<=$E$9,100%/$E$9*J49,0) -> 0 | K52: =IF(K49<=$E$9,100%/$E$9*K49,0) -> 0 | L52: =IF(L49<=$E$9,100%/$E$9*L49,0) -> 0 | M52: =IF(M49<=$E$9,100%/$E$9*M49,0) -> 0 | N52: =IF(N49<=$E$9,100%/$E$9*N49,0) -> 0 | ... Q52: =IF(Q49<=$E$9,100%/$E$9*Q49,0) -> 0
C53: % TERM OF PAYMENT PELANGGAN | D53: =SUM(E53:Q53) -> 1 | E53: 0 | F53: 1 | J53: 0 | K53: 0 | L53: 0 | M53: 0 | N53: 0 | O53: 0 | P53: 0 | Q53: 0 | R53: * sesuaikan dengan TOP
C54: % TERM OF PAYMENT KEPADA MITRA | D54: =SUM(E54:Q54) -> 1 | E54: =E53 -> 0 | F54: 1 | G54: =G53 -> 0 | H54: =H53 -> 0 | I54: =I53 -> 0 | J54: =J53 -> 0 | K54: =K53 -> 0 | L54: =L53 -> 0 | M54: =M53 -> 0 | N54: =N53 -> 0 | ... Q54: =Q53 -> 0
A55: =#REF!+1 -> #REF! | C55: =C37 -> REVENUE STREAM / CASH IN | D55: =SUM(E55:Q55) -> 1.17724e+08 | E55: =SUM(E56:E57) -> 0 | F55: =SUM(F56:F57) -> 1.17724e+08 | G55: =SUM(G56:G57) -> 0 | H55: =SUM(H56:H57) -> 0 | I55: =SUM(I56:I57) -> 0 | J55: =SUM(J56:J57) -> 0 | K55: =SUM(K56:K57) -> 0 | L55: =SUM(L56:L57) -> 0 | ... Q55: =SUM(Q56:Q57) -> 0
A56: =A55+1 -> #REF! | C56: Jasa Pelaksanaan konstruksi | D56: =SUM(E56:Q56) -> 90090090 | E56: 0 | F56: =F53*$E$38 -> 90090090 | G56: =G53*$E$38 -> 0 | H56: =H53*$E$38 -> 0 | I56: =I53*$E$38 -> 0 | J56: =J53*$E$38 -> 0 | K56: =K53*$E$38 -> 0 | L56: =L53*$E$38 -> 0 | M56: =M53*$E$38 -> 0 | ... Q56: =Q53*$E$38 -> 0
C57: =C39 -> Management Fee GSD | D57: =SUM(E57:Q57) -> 27633910 | E57: 0 | F57: =$E$39*F53 -> 27633910 | G57: =$E$39*G53 -> 0 | H57: =$E$39*H53 -> 0 | I57: =$E$39*I53 -> 0 | J57: =$E$39*J53 -> 0 | K57: =$E$39*K53 -> 0 | L57: =$E$39*L53 -> 0 | M57: =$E$39*M53 -> 0 | ... Q57: =$E$39*Q53 -> 0
A58: =#REF!+1 -> #REF! | C58: =C23 -> COST STRUCTURE / CASH OUT | D58: =SUM(E58:Q58) -> -90090090 | E58: =SUM(E59:E66) -> 0 | F58: =SUM(F59:F66) -> -90090090 | G58: =SUM(G59:G66) -> 0 | H58: =SUM(H59:H66) -> 0 | I58: =SUM(I59:I66) -> 0 | J58: =SUM(J59:J66) -> 0 | K58: =SUM(K59:K66) -> 0 | L58: =SUM(L59:L66) -> 0 | ... Q58: =SUM(Q59:Q66) -> 0
A59: =#REF!+1 -> #REF! | C59: =C24 -> Biaya Mitra Pelaksana (Exclude PPN) | D59: =SUM(E59:Q59) -> -90090090 | E59: =-E54*$E$24 -> 0 | F59: =-F54*$E$24 -> -90090090 | G59: =-G54*$E$24 -> 0 | H59: =-H54*$E$24 -> 0 | I59: =-I54*$E$24 -> 0 | J59: =-J54*$E$24 -> 0 | K59: =-K54*$E$24 -> 0 | L59: =-L54*$E$24 -> 0 | ... Q59: =-Q54*$E$24 -> 0
C60: =C25 -> BEBAN LAINNYA | D60: =SUM(E60:Q60) -> 0 | E60: 0 | F60: 0 | G60: 0 | H60: 0 | I60: 0 | J60: 0 | K60: 0 | L60: 0 | M60: 0 | N60: 0 | O60: 0 | P60: 0 | Q60: 0
C61: =C26 -> Fee Fasilitas Jaminan | D61: =SUM(E61:Q61) -> 0 | E61: =-E26 -> 0
C62: =C27 -> Admin Fasilitas Jaminan | D62: =SUM(E62:Q62) -> 0 | E62: =-E27 -> 0
C63: =C28 -> Construction Assurance Risk ( CAR) | D63: =SUM(E63:Q63) -> 0 | E63: 0 | F63: 0 | G63: 0 | H63: 0 | I63: 0 | J63: 0 | K63: 0 | L63: 0 | M63: 0 | N63: 0 | O63: 0 | P63: 0 | Q63: 0
C64: =C29 -> Iuran Jasa Konstruksi | D64: =SUM(E64:Q64) -> 0 | E64: 0 | F64: 0 | G64: 0 | H64: 0 | I64: 0 | J64: 0 | K64: 0 | L64: 0 | M64: 0 | N64: 0 | O64: 0 | P64: 0 | Q64: 0
C65: =C30 -> Biaya Pengawasan | D65: =SUM(E65:Q65) -> 0 | E65: 0 | F65: =-$E$30/($E$9) -> 0 | G65: =-$E$30/($E$9) -> 0 | H65: =-$E$30/($E$9) -> 0 | I65: =-$E$30/($E$9) -> 0 | J65: =-$E$30/($E$9) -> 0 | K65: =-$E$30/($E$9) -> 0 | L65: =-$E$30/($E$9) -> 0 | M65: =-$E$30/($E$9) -> 0 | ... Q65: =-$E$30/($E$9) -> 0
C66: =C31 -> BOP Project | D66: =SUM(E66:Q66) -> 0 | F66: =-$E$31/($E$9) -> 0
A67: =#REF!+1 -> #REF! | C67: GROSS MARGIN / EBIT | D67: =SUM(E67:Q67) -> 27633910 | E67: =E55+E58 -> 0 | F67: =F55+F58 -> 27633910 | G67: =G55+G58 -> 0 | H67: =H55+H58 -> 0 | I67: =I55+I58 -> 0 | J67: =J55+J58 -> 0 | K67: =K55+K58 -> 0 | L67: =L55+L58 -> 0 | ... Q67: =Q55+Q58 -> 0
A68: =A67+1 -> #REF! | C68: Pengurangan pph 23 | D68: =SUM(E68:Q68) -> -3119686 | E68: =-$E$21*E55 -> 0 | F68: =-$E$21*F55 -> -3119686 | G68: =-$E$21*G55 -> 0 | H68: =-$E$21*H55 -> 0 | I68: =-$E$21*I55 -> 0 | J68: =-$E$21*J55 -> 0 | K68: =-$E$21*K55 -> 0 | L68: =-$E$21*L55 -> 0 | ... Q68: =-$E$21*Q55 -> 0
C69: PPn yang harus dibayarkan | D69: =SUM(E69:Q69) -> 0
C70: PPn Keluaran | D70: =SUM(E70:Q70) -> 12949640 | E70: =11/12*12%*E55 -> 0 | F70: =11/12*12%*F55 -> 12949640 | G70: =11/12*12%*G55 -> 0 | H70: =11/12*12%*H55 -> 0 | I70: =11/12*12%*I55 -> 0 | J70: =11/12*12%*J55 -> 0 | K70: =11/12*12%*K55 -> 0 | L70: =11/12*12%*L55 -> 0 | ... Q70: =11/12*12%*Q55 -> 0
C71: PPn Masukan | D71: =SUM(E71:Q71) -> -9909909.9 | E71: =11/12*12%*E59 -> 0 | F71: =11/12*12%*F59 -> -9909909.9 | G71: =11/12*12%*G59 -> 0 | H71: =11/12*12%*H59 -> 0 | I71: =11/12*12%*I59 -> 0 | J71: =11/12*12%*J59 -> 0 | K71: =11/12*12%*K59 -> 0 | L71: =11/12*12%*L59 -> 0 | ... Q71: =11/12*12%*Q59 -> 0
C72: Kredit PPn | D72: =SUM(E72:Q72) -> -3039730.1 | E72: =-(E70+E71) -> 0 | F72: =-(F70+F71) -> -3039730.1 | G72: =-(G70+G71) -> 0 | H72: =-(H70+H71) -> 0 | I72: =-(I70+I71) -> 0 | J72: =-(J70+J71) -> 0 | K72: =-(K70+K71) -> 0 | L72: =-(L70+L71) -> 0 | ... Q72: =-(Q70+Q71) -> 0
A73: =#REF!+1 -> #REF! | C73: =G9 -> GROSS MARGIN + PPH | D73: =SUM(E73:Q73) -> 24514224 | E73: =SUM(E67:E68) -> 0 | F73: =SUM(F67:F68) -> 24514224 | G73: =SUM(G67:G68) -> 0 | H73: =SUM(H67:H68) -> 0 | I73: =SUM(I67:I68) -> 0 | J73: =SUM(J67:J68) -> 0 | K73: =SUM(K67:K68) -> 0 | L73: =SUM(L67:L68) -> 0 | ... Q73: =SUM(Q67:Q68) -> 0
C74: Penarikan Pinjaman | D74: =SUM(E74:Q74) -> 1942446 | E74: =E82 -> 1942446
C75: Pembayaran Pokok | D75: =SUM(E75:Q75) -> -1942446 | F75: =-F103 -> -1942446 | G75: =-G103 -> 0 | H75: =-H103 -> 0 | I75: =-I103 -> 0 | J75: =-J103 -> 0 | K75: =-K103 -> 0 | L75: =-L103 -> 0 | M75: =-M103 -> 0 | ... Q75: =-Q103 -> 0
A76: =A68+1 -> #REF! | C76: Biaya Provisi | D76: =SUM(E76:Q76) -> -19424.46 | E76: =-E74*1% -> -19424.46 | F76: =-F74*1% -> 0 | G76: =-G74*1% -> 0 | H76: =-H74*1% -> 0 | I76: =-I74*1% -> 0 | J76: =-J74*1% -> 0 | K76: =-K74*1% -> 0 | L76: =-L74*1% -> 0 | ... Q76: =-Q74*1% -> 0
A77: =A76+1 -> #REF! | C77: Beban Bunga | D77: =SUM(E77:Q77) -> -17627.697 | F77: =-F104 -> -17627.697 | G77: =-G104 -> 0 | H77: =-H104 -> 0 | I77: =-I104 -> 0 | J77: =-J104 -> 0 | K77: =-K104 -> 0 | L77: =-L104 -> 0 | M77: =-M104 -> 0 | ... Q77: =-Q104 -> 0
A78: =A77+1 -> #REF! | C78: CASH MARGIN | D78: =SUM(E78:Q78) -> 24477172 | E78: =E73+SUM(E74:E77) -> 1923021.5 | F78: =F73+SUM(F74:F77) -> 22554150 | G78: =G73+SUM(G74:G77) -> 0 | H78: =H73+SUM(H74:H77) -> 0 | I78: =I73+SUM(I74:I77) -> 0 | J78: =J73+SUM(J74:J77) -> 0 | K78: =K73+SUM(K74:K77) -> 0 | L78: =L73+SUM(L74:L77) -> 0 | ... Q78: =Q73+SUM(Q74:Q77) -> 0
A79: =A78+1 -> #REF! | C79: CASH FLOW | E79: =E78 -> 1923021.5 | F79: =F78+E79 -> 24477172
H80: =F79=D78 -> TRUE
F81: =1.65% -> 0.0165
E82: =F81*E37 -> 1942446
D83: OS | F83: =E84 -> 1942446 | H83: =G83-G84 -> 0 | I83: =H83-H84 -> 0 | J83: =I83-I84 -> 0 | K83: =J83-J84 -> 0 | L83: =K83-K84 -> 0 | M83: =L83-L84 -> 0 | N83: =M83-M84 -> 0 | O83: =N83-N84 -> 0 | ... Q83: =P83-P84 -> 0
D84: Pokok | E84: =SUM(F84:R84) -> 1942446 | F84: =$E$82/1 -> 1942446
D85: Bunga | F85: =($E$16/12)*1*F83 -> 17627.697 | H85: =($E$16/12)*1*H83 -> 0 | I85: =($E$16/12)*1*I83 -> 0 | J85: =($E$16/12)*1*J83 -> 0 | K85: =($E$16/12)*1*K83 -> 0 | L85: =($E$16/12)*1*L83 -> 0 | M85: =($E$16/12)*1*M83 -> 0 | N85: =($E$16/12)*1*N83 -> 0 | O85: =($E$16/12)*1*O83 -> 0 | ... Q85: =($E$16/12)*1*Q83 -> 0
E87: 0
D88: OS | M88: =E89 -> 0 | N88: =M88-M89 -> 0 | O88: =N88-N89 -> 0 | P88: =O88-O89 -> 0 | Q88: =P88-P89 -> 0
D89: Pokok | E89: =SUM(F89:R89) -> 0 | M89: =E87/5 -> 0 | N89: =F87/5 -> 0 | O89: =G87/5 -> 0 | P89: =H87/5 -> 0 | Q89: =I87/5 -> 0
D90: Bunga | M90: =($E$16/12)*1*M88 -> 0 | N90: =($E$16/12)*1*N88 -> 0 | O90: =($E$16/12)*1*O88 -> 0 | P90: =($E$16/12)*1*P88 -> 0 | Q90: =($E$16/12)*1*Q88 -> 0
E92: 0
D93: OS | P93: =E92 -> 0 | Q93: =P93-P94 -> 0
D94: Pokok | E94: =SUM(F94:R94) -> 0 | P94: =$E$92/2 -> 0 | Q94: =$E$92/2 -> 0
D95: Bunga | P95: =($E$16/12)*1*P93 -> 0 | Q95: =($E$16/12)*1*Q93 -> 0
E97: 0
D98: OS | F98: =E99 -> 0 | G98: =F98-F99 -> 0 | H98: =G98-G99 -> 0 | I98: =H98-H99 -> 0 | J98: =I98-I99 -> 0 | K98: =J98-J99 -> 0 | L98: =K98-K99 -> 0 | M98: =L98-L99 -> 0 | N98: =M98-M99 -> 0 | ... Q98: =P98-P99 -> 0
D99: Pokok | E99: =SUM(F99:R99) -> 0 | F99: =$E$97/12 -> 0 | G99: =$E$97/12 -> 0 | H99: =$E$97/12 -> 0 | I99: =$E$97/12 -> 0 | J99: =$E$97/12 -> 0 | K99: =$E$97/12 -> 0 | L99: =$E$97/12 -> 0 | M99: =$E$97/12 -> 0 | ... Q99: =$E$97/12 -> 0
D100: Bunga | F100: =($E$16/12)*1*F98 -> 0 | G100: =($E$16/12)*1*G98 -> 0 | H100: =($E$16/12)*1*H98 -> 0 | I100: =($E$16/12)*1*I98 -> 0 | J100: =($E$16/12)*1*J98 -> 0 | K100: =($E$16/12)*1*K98 -> 0 | L100: =($E$16/12)*1*L98 -> 0 | M100: =($E$16/12)*1*M98 -> 0 | ... Q100: =($E$16/12)*1*Q98 -> 0
D102: TOTAL
D103: Pokok | E103: =SUM(F103:Q103) -> 1942446 | F103: =F84+F89+F94+F99 -> 1942446 | G103: =G84+G89+G94+G99 -> 0 | H103: =H84+H89+H94+H99 -> 0 | I103: =I84+I89+I94+I99 -> 0 | J103: =J84+J89+J94+J99 -> 0 | K103: =K84+K89+K94+K99 -> 0 | L103: =L84+L89+L94+L99 -> 0 | M103: =M84+M89+M94+M99 -> 0 | ... Q103: =Q84+Q89+Q94+Q99 -> 0
D104: Bunga | E104: =SUM(F104:Q104) -> 17627.697 | F104: =F85+F90+F95+F100 -> 17627.697 | G104: =G85+G90+G95+G100 -> 0 | H104: =H85+H90+H95+H100 -> 0 | I104: =I85+I90+I95+I100 -> 0 | J104: =J85+J90+J95+J100 -> 0 | K104: =K85+K90+K95+K100 -> 0 | L104: =L85+L90+L95+L100 -> 0 | M104: =M85+M90+M95+M100 -> 0 | ... Q104: =Q85+Q90+Q95+Q100 -> 0

Sheet BBM Palapa Kupang
C2: TABEL PROFITABILITY PROJECT | G2: KESIMPULAN ANALISIS KELAYAKAN PROJECT
C3: INFORMASI PROJECT | G3: =E6 -> Pekerjaan Pengadaan BBM TTC Palapa
C4: Nama Pelanggan | E4: Telkomsel | G4: =E4 -> Telkomsel
C5: Kategori Project | E5: PS | G5: REVENUE | I5: =IF(E37=D55,E37,"perhitungan salah, CEK KEMBALI CASH FLOW DAN BLOCK REVENUE STREAM") -> 29431250 | J5: =I5=E37 -> TRUE
C6: Nama Project | E6: Pekerjaan Pengadaan BBM TTC Palapa | G6: TOTAL BEBAN/CASH OUT | I6: =IF(E23=D58*-1,E23,"perhitungan salah, CEK KEMBALI CASH FLOW DAN BLOCKCOST STRUCTURE") -> 21982187 | J6: =I6=E23 -> TRUE
C7: Lokasi Project | E7: Kupang | G7: GROSS MARGIN | H7: =I7/I5 -> 0.25310047 | I7: =I5-I6 -> 7449063.3 | J7: =I7=D67 -> TRUE
C8: Estimasi mulai pekerjaan (MM/YY) | E8: 46259 | G8: Total Pajak PPH | I8: =E41 -> 779928.12 | J8: =I8=E41 -> TRUE
A9: =IF(E9="",0,1) -> 1 | C9: Durasi Project (bulan) | E9: 1 | G9: GROSS MARGIN + PPH | H9: =I9/I5 -> 0.22660047 | I9: =I7-I8 -> 6669135.2
A10: =IF(E10="",0,1) -> 1 | C10: Durasi Retensi (bulan) | E10: 0 | G10: Provisi | I10: =D76*-1 -> 4856.1562 | J10: =I10=E45 -> TRUE
C11: Pengawasan Konstruksi Sendiri / Menggunakan MK ? | E11: Sendiri ( by GSD ) | F11: *pilihan | G11: Bunga Pinjaman | I11: =D77*-1 -> 4406.9618 | J11: =I11=E46 -> TRUE
C12: Tipe Bagunan | D12: {=IF(E37<='[128]Tabel PUPR'!A15,'[128]Tabel PUPR'!B15,IF(E37<='[128]Tabel PUPR'!A16,'[128]Tabel PUPR'!B16,IF(E37<='[128]Tabel PUPR'!A17,'[128]Tabel PUPR'!B17,IF(E37<='[128]Tabel PUPR'!A18,'[128]Tabel PUPR'!B18,IF(E37<='[128]Tabel PUPR'!A19,'[128]Tabel PUPR'!B19,IF(E37<='[128]Tabel PUPR'!A20,'[128]Tabel PUPR'!B20,IF(E37<='[128]Tabel PUPR'!A21,'[128]Tabel PUPR'!B21,IF(E37<='[128]Tabel PUPR'!A22,'[128]Tabel PUPR'!B22,IF(E37<='[128]Tabel PUPR'!A23,'[128]Tabel PUPR'!B23,IF(E37<='[128]Tabel PUPR'!A24,'[128]Tabel PUPR'!B24,IF(E37<='[128]Tabel PUPR'!A25,k,k)))))))))))} -> a | E12: Sederhana ( < 2 lantai) | F12: *pilihan | G12: NET INCOME | H12: =I12/I5 -> 0.22628573 | I12: =I9-SUM(I10:I11) -> 6659872
C13: TOP Pembayaran Kepada Mitra | E13: setelah BAST | G13: Kredit PPN | I13: =-D72 -> 819396.96
C14: TOP Pembayaran Pelanggan | E14: setelah BAST | G14: NET CASH FLOW | H14: =IF(I14>0,"Cashflow Positif","Cashflow Negatif") -> Cashflow Positif | I14: =I12-I13 -> 5840475.1 | K14: CATATAN:
C15: ASUMSI-ASUMSI | G15: CF selama kontrak | H15: =COUNTIF(E79:Q79,"<"&0) -> 0 | I15: =IF(H15>0,"Terdapat CF Negatif","All CF Positif") -> All CF Positif
A16: =IF(E10=[129]key!A3,1,0) -> 0 | C16: Suku Bunga per tahun | E16: 0.1089 | G16: KESIMPULAN | H16: =IF(H12>0%,IF(H15=0,IF(H12>10.89%,"Layak dengan Net Income sebesar",IF(I5>1000000000,IF(H12>10.89%,"Tidak Layak dengan Net income dibawah treshold ",IF(H12>0%,"Tidak Layak dengan Net income dibawah treshold","Tidak Layak dengan Net income dibawah treshold")),"Tidak Layak dengan Net income dibawah treshold")),"Tidak Layak dengan Net Income sebesar"),"Tidak Layak dengan Net income dibawah treshold") -> Layak dengan Net Income sebesar | K16: * JIKA TERDAPAT CF NEGATIF :
C17: Suku Bunga per bulan | E17: =E16/12 -> 0.009075 | H17: =H12 -> 0.22628573 | K17: 1. adjust nilai pinjaman hingga CF positif
C18: Pemodalan: Loan | E18: 1 | G18: REVENUE INCL PPN | H18: 11/12*12% | I18: =I5+D70 -> 32668688 | K18: 2. Adjust asumsi pembayaran mitra / customer, namun harus sesuai dengan
C19: Provisi | E19: 0.01 | G19: Notes lain-lain: | K19: kondisi aktual / konfirmasi dengan pihak OM
C20: PPN | E20: 0.12 | G20: =C24 -> Biaya Mitra Pelaksana (Exclude PPN) | I20: =E24 -> 21982187
C21: PPH pasal 23 | E21: 0.0265 | G21: =C31 -> BOP Project | I21: =E31 -> 0
C22: Periode Pinjaman (Bulan) | E22: =E9 -> 1 | G22: =C39 -> Management Fee GSD | I22: =E39 -> 7449063.3
C23: COST STRUCTURE / CASH OUT | E23: =SUM(E24:E31) -> 21982187
C24: Biaya Mitra Pelaksana (Exclude PPN) | E24: =COGS!H9 -> 21982187
C25: BEBAN LAINNYA | E25: 0
C26: Fee Fasilitas Jaminan | F26: * Minimal 500rb dengan catatan apabila contohnya: 1. Nilai Proyek 10M 2. Jangka waktu kerjasama adalah 3 bulan 3. Nilai Jaminan Dipersyaratkan 15% Maka Cost untuk fee: =(((0.5%/12)x3)x(15%x10M)
C27: Admin Fasilitas Jaminan | F27: * Apabila ada jaminan, biaya admin Rp 250.000,-
C28: Construction Assurance Risk ( CAR) | E28: 0
C29: Iuran Jasa Konstruksi | E29: 0
C30: Biaya Pengawasan | D30: =IF(E11='[128]Tabel PUPR'!D4,0%,VLOOKUP([128]Profitability!D12,'[128]Tabel PUPR'!B15:E25,IF([128]Profitability!E12='[128]Tabel PUPR'!A8,2,IF([128]Profitability!D12='[128]Tabel PUPR'!A9,3,4)))) -> 0 | E30: =D30*$E$24 -> 0 | F30: Berdasarkan PUPR : | G30: 0
C31: BOP Project | D31: =G31 -> 0 | E31: =D31*$E$24 -> 0 | F31: Berdasarkan PUPR : | G31: 0 | H31: *% bisa disesuaikan dengan asumsi sendiri pada kolom D31
C32: JAMINAN - JAMINAN | E32: =SUM(E33:E36) -> 0
C33: Jaminan Uang muka | D33: 0 | E33: =D33*$E$37 -> 0 | F33: * cek dan sesuaikan pengenaan % terhadap revenue / isi nilai manual pada kolom E
C34: Jaminan Penawaran | D34: 0 | E34: =D34*$E$37 -> 0 | F34: * cek dan sesuaikan pengenaan % terhadap revenue / isi nilai manual pada kolom E
C35: Jaminan Pelaksanaan | D35: 0 | E35: =D35*$E$37 -> 0 | F35: * cek dan sesuaikan pengenaan % terhadap revenue / isi nilai manual pada kolom E
C36: Jaminan Pemeliharaan | D36: 0 | E36: =D36*$E$37 -> 0 | F36: * cek dan sesuaikan pengenaan % terhadap revenue / isi nilai manual pada kolom E
C37: REVENUE STREAM / CASH IN | E37: =SUM(E38:E39) -> 29431250 | G37: 29431250
C38: Jasa Pelaksanaan konstruksi | E38: =E24 -> 21982187
C39: Management Fee GSD | D39: 0.33886816 | E39: =D39*SUM(E38) -> 7449063.3 | F39: *terhadap nilai mitra
C40: PERPAJAKAN
C41: PPh | E41: =D68*-1 -> 779928.12
C42: PPn | E42: =D72*-1 -> 819396.96
C43: PINJAMAN
C44: Besar Pinjaman | E44: =D74 -> 485615.62 | G44: Islam Fahri Rahman | I44: Hendroyono | K44: Abimanyu
C45: Biaya Provisi | E45: =-D76 -> 4856.1562 | G45: Mgr Product & Solution | I45: Mgr Planning & Delivery | K45: Mgr Marketing, Sales & Solution
C46: Bunga Pinjaman | E46: =D77*-1 -> 4406.9618
C48: CASHFLOW PROJECT
C49: Jangka Waktu | D49: Total | E49: 0 | F49: 1 | G49: 2 | H49: 3 | I49: 4 | J49: 5 | K49: 6 | L49: 7 | M49: 8 | N49: 9 | O49: 10 | P49: 11 | Q49: 12
A50: 1 | C50: Bulan | E50: =E8 -> 46259 | F50: =EDATE(E50,1) -> 46290 | G50: =EDATE(F50,1) -> 46320 | H50: =EDATE(G50,1) -> 46351 | I50: =EDATE(H50,1) -> 46381 | J50: =EDATE(I50,1) -> 46412 | K50: =EDATE(J50,1) -> 46443 | L50: =EDATE(K50,1) -> 46471 | M50: =EDATE(L50,1) -> 46502 | ... Q50: =EDATE(P50,1) -> 46624
A51: =A50+1 -> 2 | C51: TOP (progress)
C52: % PROGRESS PEKERJAAN | D52: =MAX(E52:Q52) -> 1 | E52: 0 | F52: 1 | G52: =IF(G49<=$E$9,100%/$E$9*G49,0) -> 0 | H52: =IF(H49<=$E$9,100%/$E$9*H49,0) -> 0 | I52: =IF(I49<=$E$9,100%/$E$9*I49,0) -> 0 | J52: =IF(J49<=$E$9,100%/$E$9*J49,0) -> 0 | K52: =IF(K49<=$E$9,100%/$E$9*K49,0) -> 0 | L52: =IF(L49<=$E$9,100%/$E$9*L49,0) -> 0 | M52: =IF(M49<=$E$9,100%/$E$9*M49,0) -> 0 | N52: =IF(N49<=$E$9,100%/$E$9*N49,0) -> 0 | ... Q52: =IF(Q49<=$E$9,100%/$E$9*Q49,0) -> 0
C53: % TERM OF PAYMENT PELANGGAN | D53: =SUM(E53:Q53) -> 1 | E53: 0 | F53: 1 | J53: 0 | K53: 0 | L53: 0 | M53: 0 | N53: 0 | O53: 0 | P53: 0 | Q53: 0 | R53: * sesuaikan dengan TOP
C54: % TERM OF PAYMENT KEPADA MITRA | D54: =SUM(E54:Q54) -> 1 | E54: =E53 -> 0 | F54: 1 | G54: =G53 -> 0 | H54: =H53 -> 0 | I54: =I53 -> 0 | J54: =J53 -> 0 | K54: =K53 -> 0 | L54: =L53 -> 0 | M54: =M53 -> 0 | N54: =N53 -> 0 | ... Q54: =Q53 -> 0
A55: =#REF!+1 -> #REF! | C55: =C37 -> REVENUE STREAM / CASH IN | D55: =SUM(E55:Q55) -> 29431250 | E55: =SUM(E56:E57) -> 0 | F55: =SUM(F56:F57) -> 29431250 | G55: =SUM(G56:G57) -> 0 | H55: =SUM(H56:H57) -> 0 | I55: =SUM(I56:I57) -> 0 | J55: =SUM(J56:J57) -> 0 | K55: =SUM(K56:K57) -> 0 | L55: =SUM(L56:L57) -> 0 | ... Q55: =SUM(Q56:Q57) -> 0
A56: =A55+1 -> #REF! | C56: Jasa Pelaksanaan konstruksi | D56: =SUM(E56:Q56) -> 21982187 | E56: 0 | F56: =F53*$E$38 -> 21982187 | G56: =G53*$E$38 -> 0 | H56: =H53*$E$38 -> 0 | I56: =I53*$E$38 -> 0 | J56: =J53*$E$38 -> 0 | K56: =K53*$E$38 -> 0 | L56: =L53*$E$38 -> 0 | M56: =M53*$E$38 -> 0 | ... Q56: =Q53*$E$38 -> 0
C57: =C39 -> Management Fee GSD | D57: =SUM(E57:Q57) -> 7449063.3 | E57: 0 | F57: =$E$39*F53 -> 7449063.3 | G57: =$E$39*G53 -> 0 | H57: =$E$39*H53 -> 0 | I57: =$E$39*I53 -> 0 | J57: =$E$39*J53 -> 0 | K57: =$E$39*K53 -> 0 | L57: =$E$39*L53 -> 0 | M57: =$E$39*M53 -> 0 | ... Q57: =$E$39*Q53 -> 0
A58: =#REF!+1 -> #REF! | C58: =C23 -> COST STRUCTURE / CASH OUT | D58: =SUM(E58:Q58) -> -21982187 | E58: =SUM(E59:E66) -> 0 | F58: =SUM(F59:F66) -> -21982187 | G58: =SUM(G59:G66) -> 0 | H58: =SUM(H59:H66) -> 0 | I58: =SUM(I59:I66) -> 0 | J58: =SUM(J59:J66) -> 0 | K58: =SUM(K59:K66) -> 0 | L58: =SUM(L59:L66) -> 0 | ... Q58: =SUM(Q59:Q66) -> 0
A59: =#REF!+1 -> #REF! | C59: =C24 -> Biaya Mitra Pelaksana (Exclude PPN) | D59: =SUM(E59:Q59) -> -21982187 | E59: =-E54*$E$24 -> 0 | F59: =-F54*$E$24 -> -21982187 | G59: =-G54*$E$24 -> 0 | H59: =-H54*$E$24 -> 0 | I59: =-I54*$E$24 -> 0 | J59: =-J54*$E$24 -> 0 | K59: =-K54*$E$24 -> 0 | L59: =-L54*$E$24 -> 0 | ... Q59: =-Q54*$E$24 -> 0
C60: =C25 -> BEBAN LAINNYA | D60: =SUM(E60:Q60) -> 0 | E60: 0 | F60: 0 | G60: 0 | H60: 0 | I60: 0 | J60: 0 | K60: 0 | L60: 0 | M60: 0 | N60: 0 | O60: 0 | P60: 0 | Q60: 0
C61: =C26 -> Fee Fasilitas Jaminan | D61: =SUM(E61:Q61) -> 0 | E61: =-E26 -> 0
C62: =C27 -> Admin Fasilitas Jaminan | D62: =SUM(E62:Q62) -> 0 | E62: =-E27 -> 0
C63: =C28 -> Construction Assurance Risk ( CAR) | D63: =SUM(E63:Q63) -> 0 | E63: 0 | F63: 0 | G63: 0 | H63: 0 | I63: 0 | J63: 0 | K63: 0 | L63: 0 | M63: 0 | N63: 0 | O63: 0 | P63: 0 | Q63: 0
C64: =C29 -> Iuran Jasa Konstruksi | D64: =SUM(E64:Q64) -> 0 | E64: 0 | F64: 0 | G64: 0 | H64: 0 | I64: 0 | J64: 0 | K64: 0 | L64: 0 | M64: 0 | N64: 0 | O64: 0 | P64: 0 | Q64: 0
C65: =C30 -> Biaya Pengawasan | D65: =SUM(E65:Q65) -> 0 | E65: 0 | F65: =-$E$30/($E$9) -> 0 | G65: =-$E$30/($E$9) -> 0 | H65: =-$E$30/($E$9) -> 0 | I65: =-$E$30/($E$9) -> 0 | J65: =-$E$30/($E$9) -> 0 | K65: =-$E$30/($E$9) -> 0 | L65: =-$E$30/($E$9) -> 0 | M65: =-$E$30/($E$9) -> 0 | ... Q65: =-$E$30/($E$9) -> 0
C66: =C31 -> BOP Project | D66: =SUM(E66:Q66) -> 0 | F66: =-$E$31/($E$9) -> 0
A67: =#REF!+1 -> #REF! | C67: GROSS MARGIN / EBIT | D67: =SUM(E67:Q67) -> 7449063.3 | E67: =E55+E58 -> 0 | F67: =F55+F58 -> 7449063.3 | G67: =G55+G58 -> 0 | H67: =H55+H58 -> 0 | I67: =I55+I58 -> 0 | J67: =J55+J58 -> 0 | K67: =K55+K58 -> 0 | L67: =L55+L58 -> 0 | ... Q67: =Q55+Q58 -> 0
A68: =A67+1 -> #REF! | C68: Pengurangan pph 23 | D68: =SUM(E68:Q68) -> -779928.12 | E68: =-$E$21*E55 -> 0 | F68: =-$E$21*F55 -> -779928.12 | G68: =-$E$21*G55 -> 0 | H68: =-$E$21*H55 -> 0 | I68: =-$E$21*I55 -> 0 | J68: =-$E$21*J55 -> 0 | K68: =-$E$21*K55 -> 0 | L68: =-$E$21*L55 -> 0 | ... Q68: =-$E$21*Q55 -> 0
C69: PPn yang harus dibayarkan | D69: =SUM(E69:Q69) -> 0
C70: PPn Keluaran | D70: =SUM(E70:Q70) -> 3237437.5 | E70: =11/12*12%*E55 -> 0 | F70: =11/12*12%*F55 -> 3237437.5 | G70: =11/12*12%*G55 -> 0 | H70: =11/12*12%*H55 -> 0 | I70: =11/12*12%*I55 -> 0 | J70: =11/12*12%*J55 -> 0 | K70: =11/12*12%*K55 -> 0 | L70: =11/12*12%*L55 -> 0 | ... Q70: =11/12*12%*Q55 -> 0
C71: PPn Masukan | D71: =SUM(E71:Q71) -> -2418040.5 | E71: =11/12*12%*E59 -> 0 | F71: =11/12*12%*F59 -> -2418040.5 | G71: =11/12*12%*G59 -> 0 | H71: =11/12*12%*H59 -> 0 | I71: =11/12*12%*I59 -> 0 | J71: =11/12*12%*J59 -> 0 | K71: =11/12*12%*K59 -> 0 | L71: =11/12*12%*L59 -> 0 | ... Q71: =11/12*12%*Q59 -> 0
C72: Kredit PPn | D72: =SUM(E72:Q72) -> -819396.96 | E72: =-(E70+E71) -> 0 | F72: =-(F70+F71) -> -819396.96 | G72: =-(G70+G71) -> 0 | H72: =-(H70+H71) -> 0 | I72: =-(I70+I71) -> 0 | J72: =-(J70+J71) -> 0 | K72: =-(K70+K71) -> 0 | L72: =-(L70+L71) -> 0 | ... Q72: =-(Q70+Q71) -> 0
A73: =#REF!+1 -> #REF! | C73: =G9 -> GROSS MARGIN + PPH | D73: =SUM(E73:Q73) -> 6669135.2 | E73: =SUM(E67:E68) -> 0 | F73: =SUM(F67:F68) -> 6669135.2 | G73: =SUM(G67:G68) -> 0 | H73: =SUM(H67:H68) -> 0 | I73: =SUM(I67:I68) -> 0 | J73: =SUM(J67:J68) -> 0 | K73: =SUM(K67:K68) -> 0 | L73: =SUM(L67:L68) -> 0 | ... Q73: =SUM(Q67:Q68) -> 0
C74: Penarikan Pinjaman | D74: =SUM(E74:Q74) -> 485615.62 | E74: =E82 -> 485615.62
C75: Pembayaran Pokok | D75: =SUM(E75:Q75) -> -485615.62 | F75: =-F103 -> -485615.62 | G75: =-G103 -> 0 | H75: =-H103 -> 0 | I75: =-I103 -> 0 | J75: =-J103 -> 0 | K75: =-K103 -> 0 | L75: =-L103 -> 0 | M75: =-M103 -> 0 | ... Q75: =-Q103 -> 0
A76: =A68+1 -> #REF! | C76: Biaya Provisi | D76: =SUM(E76:Q76) -> -4856.1562 | E76: =-E74*1% -> -4856.1562 | F76: =-F74*1% -> 0 | G76: =-G74*1% -> 0 | H76: =-H74*1% -> 0 | I76: =-I74*1% -> 0 | J76: =-J74*1% -> 0 | K76: =-K74*1% -> 0 | L76: =-L74*1% -> 0 | ... Q76: =-Q74*1% -> 0
A77: =A76+1 -> #REF! | C77: Beban Bunga | D77: =SUM(E77:Q77) -> -4406.9618 | F77: =-F104 -> -4406.9618 | G77: =-G104 -> 0 | H77: =-H104 -> 0 | I77: =-I104 -> 0 | J77: =-J104 -> 0 | K77: =-K104 -> 0 | L77: =-L104 -> 0 | M77: =-M104 -> 0 | ... Q77: =-Q104 -> 0
A78: =A77+1 -> #REF! | C78: CASH MARGIN | D78: =SUM(E78:Q78) -> 6659872 | E78: =E73+SUM(E74:E77) -> 480759.47 | F78: =F73+SUM(F74:F77) -> 6179112.6 | G78: =G73+SUM(G74:G77) -> 0 | H78: =H73+SUM(H74:H77) -> 0 | I78: =I73+SUM(I74:I77) -> 0 | J78: =J73+SUM(J74:J77) -> 0 | K78: =K73+SUM(K74:K77) -> 0 | L78: =L73+SUM(L74:L77) -> 0 | ... Q78: =Q73+SUM(Q74:Q77) -> 0
A79: =A78+1 -> #REF! | C79: CASH FLOW | E79: =E78 -> 480759.47 | F79: =F78+E79 -> 6659872
H80: =F79=D78 -> TRUE
F81: =1.65% -> 0.0165
E82: =F81*E37 -> 485615.62
D83: OS | F83: =E84 -> 485615.62 | H83: =G83-G84 -> 0 | I83: =H83-H84 -> 0 | J83: =I83-I84 -> 0 | K83: =J83-J84 -> 0 | L83: =K83-K84 -> 0 | M83: =L83-L84 -> 0 | N83: =M83-M84 -> 0 | O83: =N83-N84 -> 0 | ... Q83: =P83-P84 -> 0
D84: Pokok | E84: =SUM(F84:R84) -> 485615.62 | F84: =$E$82/1 -> 485615.62
D85: Bunga | F85: =($E$16/12)*1*F83 -> 4406.9618 | H85: =($E$16/12)*1*H83 -> 0 | I85: =($E$16/12)*1*I83 -> 0 | J85: =($E$16/12)*1*J83 -> 0 | K85: =($E$16/12)*1*K83 -> 0 | L85: =($E$16/12)*1*L83 -> 0 | M85: =($E$16/12)*1*M83 -> 0 | N85: =($E$16/12)*1*N83 -> 0 | O85: =($E$16/12)*1*O83 -> 0 | ... Q85: =($E$16/12)*1*Q83 -> 0
E87: 0
D88: OS | M88: =E89 -> 0 | N88: =M88-M89 -> 0 | O88: =N88-N89 -> 0 | P88: =O88-O89 -> 0 | Q88: =P88-P89 -> 0
D89: Pokok | E89: =SUM(F89:R89) -> 0 | M89: =E87/5 -> 0 | N89: =F87/5 -> 0 | O89: =G87/5 -> 0 | P89: =H87/5 -> 0 | Q89: =I87/5 -> 0
D90: Bunga | M90: =($E$16/12)*1*M88 -> 0 | N90: =($E$16/12)*1*N88 -> 0 | O90: =($E$16/12)*1*O88 -> 0 | P90: =($E$16/12)*1*P88 -> 0 | Q90: =($E$16/12)*1*Q88 -> 0
E92: 0
D93: OS | P93: =E92 -> 0 | Q93: =P93-P94 -> 0
D94: Pokok | E94: =SUM(F94:R94) -> 0 | P94: =$E$92/2 -> 0 | Q94: =$E$92/2 -> 0
D95: Bunga | P95: =($E$16/12)*1*P93 -> 0 | Q95: =($E$16/12)*1*Q93 -> 0
E97: 0
D98: OS | F98: =E99 -> 0 | G98: =F98-F99 -> 0 | H98: =G98-G99 -> 0 | I98: =H98-H99 -> 0 | J98: =I98-I99 -> 0 | K98: =J98-J99 -> 0 | L98: =K98-K99 -> 0 | M98: =L98-L99 -> 0 | N98: =M98-M99 -> 0 | ... Q98: =P98-P99 -> 0
D99: Pokok | E99: =SUM(F99:R99) -> 0 | F99: =$E$97/12 -> 0 | G99: =$E$97/12 -> 0 | H99: =$E$97/12 -> 0 | I99: =$E$97/12 -> 0 | J99: =$E$97/12 -> 0 | K99: =$E$97/12 -> 0 | L99: =$E$97/12 -> 0 | M99: =$E$97/12 -> 0 | ... Q99: =$E$97/12 -> 0
D100: Bunga | F100: =($E$16/12)*1*F98 -> 0 | G100: =($E$16/12)*1*G98 -> 0 | H100: =($E$16/12)*1*H98 -> 0 | I100: =($E$16/12)*1*I98 -> 0 | J100: =($E$16/12)*1*J98 -> 0 | K100: =($E$16/12)*1*K98 -> 0 | L100: =($E$16/12)*1*L98 -> 0 | M100: =($E$16/12)*1*M98 -> 0 | ... Q100: =($E$16/12)*1*Q98 -> 0
D102: TOTAL
D103: Pokok | E103: =SUM(F103:Q103) -> 485615.62 | F103: =F84+F89+F94+F99 -> 485615.62 | G103: =G84+G89+G94+G99 -> 0 | H103: =H84+H89+H94+H99 -> 0 | I103: =I84+I89+I94+I99 -> 0 | J103: =J84+J89+J94+J99 -> 0 | K103: =K84+K89+K94+K99 -> 0 | L103: =L84+L89+L94+L99 -> 0 | M103: =M84+M89+M94+M99 -> 0 | ... Q103: =Q84+Q89+Q94+Q99 -> 0
D104: Bunga | E104: =SUM(F104:Q104) -> 4406.9618 | F104: =F85+F90+F95+F100 -> 4406.9618 | G104: =G85+G90+G95+G100 -> 0 | H104: =H85+H90+H95+H100 -> 0 | I104: =I85+I90+I95+I100 -> 0 | J104: =J85+J90+J95+J100 -> 0 | K104: =K85+K90+K95+K100 -> 0 | L104: =L85+L90+L95+L100 -> 0 | M104: =M85+M90+M95+M100 -> 0 | ... Q104: =Q85+Q90+Q95+Q100 -> 0

Sheet BBM Gombel
C2: TABEL PROFITABILITY PROJECT | G2: KESIMPULAN ANALISIS KELAYAKAN PROJECT
C3: INFORMASI PROJECT | G3: =E6 -> Pekerjaan Pengadaan BBM TTC Gombel
C4: Nama Pelanggan | E4: Telkomsel | G4: =E4 -> Telkomsel
C5: Kategori Project | E5: PS | G5: REVENUE | I5: =IF(E37=D55,E37,"perhitungan salah, CEK KEMBALI CASH FLOW DAN BLOCK REVENUE STREAM") -> 58862000 | J5: =I5=E37 -> TRUE
C6: Nama Project | E6: Pekerjaan Pengadaan BBM TTC Gombel | G6: TOTAL BEBAN/CASH OUT | I6: =IF(E23=D58*-1,E23,"perhitungan salah, CEK KEMBALI CASH FLOW DAN BLOCKCOST STRUCTURE") -> 36400000 | J6: =I6=E23 -> TRUE
C7: Lokasi Project | E7: Kupang | G7: GROSS MARGIN | H7: =I7/I5 -> 0.38160443 | I7: =I5-I6 -> 22462000 | J7: =I7=D67 -> TRUE
C8: Estimasi mulai pekerjaan (MM/YY) | E8: 46259 | G8: Total Pajak PPH | I8: =E41 -> 1559843 | J8: =I8=E41 -> TRUE
A9: =IF(E9="",0,1) -> 1 | C9: Durasi Project (bulan) | E9: 1 | G9: GROSS MARGIN + PPH | H9: =I9/I5 -> 0.35510443 | I9: =I7-I8 -> 20902157
A10: =IF(E10="",0,1) -> 1 | C10: Durasi Retensi (bulan) | E10: 0 | G10: Provisi | I10: =D76*-1 -> 9712.23 | J10: =I10=E45 -> TRUE
C11: Pengawasan Konstruksi Sendiri / Menggunakan MK ? | E11: Sendiri ( by GSD ) | F11: *pilihan | G11: Bunga Pinjaman | I11: =D77*-1 -> 8813.8487 | J11: =I11=E46 -> TRUE
C12: Tipe Bagunan | D12: {=IF(E37<='[128]Tabel PUPR'!A15,'[128]Tabel PUPR'!B15,IF(E37<='[128]Tabel PUPR'!A16,'[128]Tabel PUPR'!B16,IF(E37<='[128]Tabel PUPR'!A17,'[128]Tabel PUPR'!B17,IF(E37<='[128]Tabel PUPR'!A18,'[128]Tabel PUPR'!B18,IF(E37<='[128]Tabel PUPR'!A19,'[128]Tabel PUPR'!B19,IF(E37<='[128]Tabel PUPR'!A20,'[128]Tabel PUPR'!B20,IF(E37<='[128]Tabel PUPR'!A21,'[128]Tabel PUPR'!B21,IF(E37<='[128]Tabel PUPR'!A22,'[128]Tabel PUPR'!B22,IF(E37<='[128]Tabel PUPR'!A23,'[128]Tabel PUPR'!B23,IF(E37<='[128]Tabel PUPR'!A24,'[128]Tabel PUPR'!B24,IF(E37<='[128]Tabel PUPR'!A25,k,k)))))))))))} -> a | E12: Sederhana ( < 2 lantai) | F12: *pilihan | G12: NET INCOME | H12: =I12/I5 -> 0.35478969 | I12: =I9-SUM(I10:I11) -> 20883631
C13: TOP Pembayaran Kepada Mitra | E13: setelah BAST | G13: Kredit PPN | I13: =-D72 -> 2470820
C14: TOP Pembayaran Pelanggan | E14: setelah BAST | G14: NET CASH FLOW | H14: =IF(I14>0,"Cashflow Positif","Cashflow Negatif") -> Cashflow Positif | I14: =I12-I13 -> 18412811 | K14: CATATAN:
C15: ASUMSI-ASUMSI | G15: CF selama kontrak | H15: =COUNTIF(E79:Q79,"<"&0) -> 0 | I15: =IF(H15>0,"Terdapat CF Negatif","All CF Positif") -> All CF Positif
A16: =IF(E10=[129]key!A3,1,0) -> 0 | C16: Suku Bunga per tahun | E16: 0.1089 | G16: KESIMPULAN | H16: =IF(H12>0%,IF(H15=0,IF(H12>10.89%,"Layak dengan Net Income sebesar",IF(I5>1000000000,IF(H12>10.89%,"Tidak Layak dengan Net income dibawah treshold ",IF(H12>0%,"Tidak Layak dengan Net income dibawah treshold","Tidak Layak dengan Net income dibawah treshold")),"Tidak Layak dengan Net income dibawah treshold")),"Tidak Layak dengan Net Income sebesar"),"Tidak Layak dengan Net income dibawah treshold") -> Layak dengan Net Income sebesar | K16: * JIKA TERDAPAT CF NEGATIF :
C17: Suku Bunga per bulan | E17: =E16/12 -> 0.009075 | H17: =H12 -> 0.35478969 | K17: 1. adjust nilai pinjaman hingga CF positif
C18: Pemodalan: Loan | E18: 1 | G18: REVENUE INCL PPN | H18: 11/12*12% | I18: =I5+D70 -> 65336820 | K18: 2. Adjust asumsi pembayaran mitra / customer, namun harus sesuai dengan
C19: Provisi | E19: 0.01 | G19: Notes lain-lain: | K19: kondisi aktual / konfirmasi dengan pihak OM
C20: PPN | E20: 0.12 | G20: =C24 -> Biaya Mitra Pelaksana (Exclude PPN) | I20: =E24 -> 36400000
C21: PPH pasal 23 | E21: 0.0265 | G21: =C31 -> BOP Project | I21: =E31 -> 0
C22: Periode Pinjaman (Bulan) | E22: =E9 -> 1 | G22: =C39 -> Management Fee GSD | I22: =E39 -> 22462000
C23: COST STRUCTURE / CASH OUT | E23: =SUM(E24:E31) -> 36400000
C24: Biaya Mitra Pelaksana (Exclude PPN) | E24: =COGS!H10 -> 36400000
C25: BEBAN LAINNYA | E25: 0
C26: Fee Fasilitas Jaminan | F26: * Minimal 500rb dengan catatan apabila contohnya: 1. Nilai Proyek 10M 2. Jangka waktu kerjasama adalah 3 bulan 3. Nilai Jaminan Dipersyaratkan 15% Maka Cost untuk fee: =(((0.5%/12)x3)x(15%x10M)
C27: Admin Fasilitas Jaminan | F27: * Apabila ada jaminan, biaya admin Rp 250.000,-
C28: Construction Assurance Risk ( CAR) | E28: 0
C29: Iuran Jasa Konstruksi | E29: 0
C30: Biaya Pengawasan | D30: =IF(E11='[128]Tabel PUPR'!D4,0%,VLOOKUP([128]Profitability!D12,'[128]Tabel PUPR'!B15:E25,IF([128]Profitability!E12='[128]Tabel PUPR'!A8,2,IF([128]Profitability!D12='[128]Tabel PUPR'!A9,3,4)))) -> 0 | E30: =D30*$E$24 -> 0 | F30: Berdasarkan PUPR : | G30: 0
C31: BOP Project | D31: =G31 -> 0 | E31: =D31*$E$24 -> 0 | F31: Berdasarkan PUPR : | G31: 0 | H31: *% bisa disesuaikan dengan asumsi sendiri pada kolom D31
C32: JAMINAN - JAMINAN | E32: =SUM(E33:E36) -> 0
C33: Jaminan Uang muka | D33: 0 | E33: =D33*$E$37 -> 0 | F33: * cek dan sesuaikan pengenaan % terhadap revenue / isi nilai manual pada kolom E
C34: Jaminan Penawaran | D34: 0 | E34: =D34*$E$37 -> 0 | F34: * cek dan sesuaikan pengenaan % terhadap revenue / isi nilai manual pada kolom E
C35: Jaminan Pelaksanaan | D35: 0 | E35: =D35*$E$37 -> 0 | F35: * cek dan sesuaikan pengenaan % terhadap revenue / isi nilai manual pada kolom E
C36: Jaminan Pemeliharaan | D36: 0 | E36: =D36*$E$37 -> 0 | F36: * cek dan sesuaikan pengenaan % terhadap revenue / isi nilai manual pada kolom E
C37: REVENUE STREAM / CASH IN | E37: =SUM(E38:E39) -> 58862000 | G37: 58862000
C38: Jasa Pelaksanaan konstruksi | E38: =E24 -> 36400000
C39: Management Fee GSD | D39: 0.61708791 | E39: =D39*SUM(E38) -> 22462000 | F39: *terhadap nilai mitra
C40: PERPAJAKAN
C41: PPh | E41: =D68*-1 -> 1559843
C42: PPn | E42: =D72*-1 -> 2470820
C43: PINJAMAN
C44: Besar Pinjaman | E44: =D74 -> 971223 | G44: Islam Fahri Rahman | I44: Hendroyono | K44: Abimanyu
C45: Biaya Provisi | E45: =-D76 -> 9712.23 | G45: Mgr Product & Solution | I45: Mgr Planning & Delivery | K45: Mgr Marketing, Sales & Solution
C46: Bunga Pinjaman | E46: =D77*-1 -> 8813.8487
C48: CASHFLOW PROJECT
C49: Jangka Waktu | D49: Total | E49: 0 | F49: 1 | G49: 2 | H49: 3 | I49: 4 | J49: 5 | K49: 6 | L49: 7 | M49: 8 | N49: 9 | O49: 10 | P49: 11 | Q49: 12
A50: 1 | C50: Bulan | E50: =E8 -> 46259 | F50: =EDATE(E50,1) -> 46290 | G50: =EDATE(F50,1) -> 46320 | H50: =EDATE(G50,1) -> 46351 | I50: =EDATE(H50,1) -> 46381 | J50: =EDATE(I50,1) -> 46412 | K50: =EDATE(J50,1) -> 46443 | L50: =EDATE(K50,1) -> 46471 | M50: =EDATE(L50,1) -> 46502 | ... Q50: =EDATE(P50,1) -> 46624
A51: =A50+1 -> 2 | C51: TOP (progress)
C52: % PROGRESS PEKERJAAN | D52: =MAX(E52:Q52) -> 1 | E52: 0 | F52: 1 | G52: =IF(G49<=$E$9,100%/$E$9*G49,0) -> 0 | H52: =IF(H49<=$E$9,100%/$E$9*H49,0) -> 0 | I52: =IF(I49<=$E$9,100%/$E$9*I49,0) -> 0 | J52: =IF(J49<=$E$9,100%/$E$9*J49,0) -> 0 | K52: =IF(K49<=$E$9,100%/$E$9*K49,0) -> 0 | L52: =IF(L49<=$E$9,100%/$E$9*L49,0) -> 0 | M52: =IF(M49<=$E$9,100%/$E$9*M49,0) -> 0 | N52: =IF(N49<=$E$9,100%/$E$9*N49,0) -> 0 | ... Q52: =IF(Q49<=$E$9,100%/$E$9*Q49,0) -> 0
C53: % TERM OF PAYMENT PELANGGAN | D53: =SUM(E53:Q53) -> 1 | E53: 0 | F53: 1 | J53: 0 | K53: 0 | L53: 0 | M53: 0 | N53: 0 | O53: 0 | P53: 0 | Q53: 0 | R53: * sesuaikan dengan TOP
C54: % TERM OF PAYMENT KEPADA MITRA | D54: =SUM(E54:Q54) -> 1 | E54: =E53 -> 0 | F54: 1 | G54: =G53 -> 0 | H54: =H53 -> 0 | I54: =I53 -> 0 | J54: =J53 -> 0 | K54: =K53 -> 0 | L54: =L53 -> 0 | M54: =M53 -> 0 | N54: =N53 -> 0 | ... Q54: =Q53 -> 0
A55: =#REF!+1 -> #REF! | C55: =C37 -> REVENUE STREAM / CASH IN | D55: =SUM(E55:Q55) -> 58862000 | E55: =SUM(E56:E57) -> 0 | F55: =SUM(F56:F57) -> 58862000 | G55: =SUM(G56:G57) -> 0 | H55: =SUM(H56:H57) -> 0 | I55: =SUM(I56:I57) -> 0 | J55: =SUM(J56:J57) -> 0 | K55: =SUM(K56:K57) -> 0 | L55: =SUM(L56:L57) -> 0 | ... Q55: =SUM(Q56:Q57) -> 0
A56: =A55+1 -> #REF! | C56: Jasa Pelaksanaan konstruksi | D56: =SUM(E56:Q56) -> 36400000 | E56: 0 | F56: =F53*$E$38 -> 36400000 | G56: =G53*$E$38 -> 0 | H56: =H53*$E$38 -> 0 | I56: =I53*$E$38 -> 0 | J56: =J53*$E$38 -> 0 | K56: =K53*$E$38 -> 0 | L56: =L53*$E$38 -> 0 | M56: =M53*$E$38 -> 0 | ... Q56: =Q53*$E$38 -> 0
C57: =C39 -> Management Fee GSD | D57: =SUM(E57:Q57) -> 22462000 | E57: 0 | F57: =$E$39*F53 -> 22462000 | G57: =$E$39*G53 -> 0 | H57: =$E$39*H53 -> 0 | I57: =$E$39*I53 -> 0 | J57: =$E$39*J53 -> 0 | K57: =$E$39*K53 -> 0 | L57: =$E$39*L53 -> 0 | M57: =$E$39*M53 -> 0 | ... Q57: =$E$39*Q53 -> 0
A58: =#REF!+1 -> #REF! | C58: =C23 -> COST STRUCTURE / CASH OUT | D58: =SUM(E58:Q58) -> -36400000 | E58: =SUM(E59:E66) -> 0 | F58: =SUM(F59:F66) -> -36400000 | G58: =SUM(G59:G66) -> 0 | H58: =SUM(H59:H66) -> 0 | I58: =SUM(I59:I66) -> 0 | J58: =SUM(J59:J66) -> 0 | K58: =SUM(K59:K66) -> 0 | L58: =SUM(L59:L66) -> 0 | ... Q58: =SUM(Q59:Q66) -> 0
A59: =#REF!+1 -> #REF! | C59: =C24 -> Biaya Mitra Pelaksana (Exclude PPN) | D59: =SUM(E59:Q59) -> -36400000 | E59: =-E54*$E$24 -> 0 | F59: =-F54*$E$24 -> -36400000 | G59: =-G54*$E$24 -> 0 | H59: =-H54*$E$24 -> 0 | I59: =-I54*$E$24 -> 0 | J59: =-J54*$E$24 -> 0 | K59: =-K54*$E$24 -> 0 | L59: =-L54*$E$24 -> 0 | ... Q59: =-Q54*$E$24 -> 0
C60: =C25 -> BEBAN LAINNYA | D60: =SUM(E60:Q60) -> 0 | E60: 0 | F60: 0 | G60: 0 | H60: 0 | I60: 0 | J60: 0 | K60: 0 | L60: 0 | M60: 0 | N60: 0 | O60: 0 | P60: 0 | Q60: 0
C61: =C26 -> Fee Fasilitas Jaminan | D61: =SUM(E61:Q61) -> 0 | E61: =-E26 -> 0
C62: =C27 -> Admin Fasilitas Jaminan | D62: =SUM(E62:Q62) -> 0 | E62: =-E27 -> 0
C63: =C28 -> Construction Assurance Risk ( CAR) | D63: =SUM(E63:Q63) -> 0 | E63: 0 | F63: 0 | G63: 0 | H63: 0 | I63: 0 | J63: 0 | K63: 0 | L63: 0 | M63: 0 | N63: 0 | O63: 0 | P63: 0 | Q63: 0
C64: =C29 -> Iuran Jasa Konstruksi | D64: =SUM(E64:Q64) -> 0 | E64: 0 | F64: 0 | G64: 0 | H64: 0 | I64: 0 | J64: 0 | K64: 0 | L64: 0 | M64: 0 | N64: 0 | O64: 0 | P64: 0 | Q64: 0
C65: =C30 -> Biaya Pengawasan | D65: =SUM(E65:Q65) -> 0 | E65: 0 | F65: =-$E$30/($E$9) -> 0 | G65: =-$E$30/($E$9) -> 0 | H65: =-$E$30/($E$9) -> 0 | I65: =-$E$30/($E$9) -> 0 | J65: =-$E$30/($E$9) -> 0 | K65: =-$E$30/($E$9) -> 0 | L65: =-$E$30/($E$9) -> 0 | M65: =-$E$30/($E$9) -> 0 | ... Q65: =-$E$30/($E$9) -> 0
C66: =C31 -> BOP Project | D66: =SUM(E66:Q66) -> 0 | F66: =-$E$31/($E$9) -> 0
A67: =#REF!+1 -> #REF! | C67: GROSS MARGIN / EBIT | D67: =SUM(E67:Q67) -> 22462000 | E67: =E55+E58 -> 0 | F67: =F55+F58 -> 22462000 | G67: =G55+G58 -> 0 | H67: =H55+H58 -> 0 | I67: =I55+I58 -> 0 | J67: =J55+J58 -> 0 | K67: =K55+K58 -> 0 | L67: =L55+L58 -> 0 | ... Q67: =Q55+Q58 -> 0
A68: =A67+1 -> #REF! | C68: Pengurangan pph 23 | D68: =SUM(E68:Q68) -> -1559843 | E68: =-$E$21*E55 -> 0 | F68: =-$E$21*F55 -> -1559843 | G68: =-$E$21*G55 -> 0 | H68: =-$E$21*H55 -> 0 | I68: =-$E$21*I55 -> 0 | J68: =-$E$21*J55 -> 0 | K68: =-$E$21*K55 -> 0 | L68: =-$E$21*L55 -> 0 | ... Q68: =-$E$21*Q55 -> 0
C69: PPn yang harus dibayarkan | D69: =SUM(E69:Q69) -> 0
C70: PPn Keluaran | D70: =SUM(E70:Q70) -> 6474820 | E70: =11/12*12%*E55 -> 0 | F70: =11/12*12%*F55 -> 6474820 | G70: =11/12*12%*G55 -> 0 | H70: =11/12*12%*H55 -> 0 | I70: =11/12*12%*I55 -> 0 | J70: =11/12*12%*J55 -> 0 | K70: =11/12*12%*K55 -> 0 | L70: =11/12*12%*L55 -> 0 | ... Q70: =11/12*12%*Q55 -> 0
C71: PPn Masukan | D71: =SUM(E71:Q71) -> -4004000 | E71: =11/12*12%*E59 -> 0 | F71: =11/12*12%*F59 -> -4004000 | G71: =11/12*12%*G59 -> 0 | H71: =11/12*12%*H59 -> 0 | I71: =11/12*12%*I59 -> 0 | J71: =11/12*12%*J59 -> 0 | K71: =11/12*12%*K59 -> 0 | L71: =11/12*12%*L59 -> 0 | ... Q71: =11/12*12%*Q59 -> 0
C72: Kredit PPn | D72: =SUM(E72:Q72) -> -2470820 | E72: =-(E70+E71) -> 0 | F72: =-(F70+F71) -> -2470820 | G72: =-(G70+G71) -> 0 | H72: =-(H70+H71) -> 0 | I72: =-(I70+I71) -> 0 | J72: =-(J70+J71) -> 0 | K72: =-(K70+K71) -> 0 | L72: =-(L70+L71) -> 0 | ... Q72: =-(Q70+Q71) -> 0
A73: =#REF!+1 -> #REF! | C73: =G9 -> GROSS MARGIN + PPH | D73: =SUM(E73:Q73) -> 20902157 | E73: =SUM(E67:E68) -> 0 | F73: =SUM(F67:F68) -> 20902157 | G73: =SUM(G67:G68) -> 0 | H73: =SUM(H67:H68) -> 0 | I73: =SUM(I67:I68) -> 0 | J73: =SUM(J67:J68) -> 0 | K73: =SUM(K67:K68) -> 0 | L73: =SUM(L67:L68) -> 0 | ... Q73: =SUM(Q67:Q68) -> 0
C74: Penarikan Pinjaman | D74: =SUM(E74:Q74) -> 971223 | E74: =E82 -> 971223
C75: Pembayaran Pokok | D75: =SUM(E75:Q75) -> -971223 | F75: =-F103 -> -971223 | G75: =-G103 -> 0 | H75: =-H103 -> 0 | I75: =-I103 -> 0 | J75: =-J103 -> 0 | K75: =-K103 -> 0 | L75: =-L103 -> 0 | M75: =-M103 -> 0 | ... Q75: =-Q103 -> 0
A76: =A68+1 -> #REF! | C76: Biaya Provisi | D76: =SUM(E76:Q76) -> -9712.23 | E76: =-E74*1% -> -9712.23 | F76: =-F74*1% -> 0 | G76: =-G74*1% -> 0 | H76: =-H74*1% -> 0 | I76: =-I74*1% -> 0 | J76: =-J74*1% -> 0 | K76: =-K74*1% -> 0 | L76: =-L74*1% -> 0 | ... Q76: =-Q74*1% -> 0
A77: =A76+1 -> #REF! | C77: Beban Bunga | D77: =SUM(E77:Q77) -> -8813.8487 | F77: =-F104 -> -8813.8487 | G77: =-G104 -> 0 | H77: =-H104 -> 0 | I77: =-I104 -> 0 | J77: =-J104 -> 0 | K77: =-K104 -> 0 | L77: =-L104 -> 0 | M77: =-M104 -> 0 | ... Q77: =-Q104 -> 0
A78: =A77+1 -> #REF! | C78: CASH MARGIN | D78: =SUM(E78:Q78) -> 20883631 | E78: =E73+SUM(E74:E77) -> 961510.77 | F78: =F73+SUM(F74:F77) -> 19922120 | G78: =G73+SUM(G74:G77) -> 0 | H78: =H73+SUM(H74:H77) -> 0 | I78: =I73+SUM(I74:I77) -> 0 | J78: =J73+SUM(J74:J77) -> 0 | K78: =K73+SUM(K74:K77) -> 0 | L78: =L73+SUM(L74:L77) -> 0 | ... Q78: =Q73+SUM(Q74:Q77) -> 0
A79: =A78+1 -> #REF! | C79: CASH FLOW | E79: =E78 -> 961510.77 | F79: =F78+E79 -> 20883631
H80: =F79=D78 -> TRUE
F81: =1.65% -> 0.0165
E82: =F81*E37 -> 971223
D83: OS | F83: =E84 -> 971223 | H83: =G83-G84 -> 0 | I83: =H83-H84 -> 0 | J83: =I83-I84 -> 0 | K83: =J83-J84 -> 0 | L83: =K83-K84 -> 0 | M83: =L83-L84 -> 0 | N83: =M83-M84 -> 0 | O83: =N83-N84 -> 0 | ... Q83: =P83-P84 -> 0
D84: Pokok | E84: =SUM(F84:R84) -> 971223 | F84: =$E$82/1 -> 971223
D85: Bunga | F85: =($E$16/12)*1*F83 -> 8813.8487 | H85: =($E$16/12)*1*H83 -> 0 | I85: =($E$16/12)*1*I83 -> 0 | J85: =($E$16/12)*1*J83 -> 0 | K85: =($E$16/12)*1*K83 -> 0 | L85: =($E$16/12)*1*L83 -> 0 | M85: =($E$16/12)*1*M83 -> 0 | N85: =($E$16/12)*1*N83 -> 0 | O85: =($E$16/12)*1*O83 -> 0 | ... Q85: =($E$16/12)*1*Q83 -> 0
E87: 0
D88: OS | M88: =E89 -> 0 | N88: =M88-M89 -> 0 | O88: =N88-N89 -> 0 | P88: =O88-O89 -> 0 | Q88: =P88-P89 -> 0
D89: Pokok | E89: =SUM(F89:R89) -> 0 | M89: =E87/5 -> 0 | N89: =F87/5 -> 0 | O89: =G87/5 -> 0 | P89: =H87/5 -> 0 | Q89: =I87/5 -> 0
D90: Bunga | M90: =($E$16/12)*1*M88 -> 0 | N90: =($E$16/12)*1*N88 -> 0 | O90: =($E$16/12)*1*O88 -> 0 | P90: =($E$16/12)*1*P88 -> 0 | Q90: =($E$16/12)*1*Q88 -> 0
E92: 0
D93: OS | P93: =E92 -> 0 | Q93: =P93-P94 -> 0
D94: Pokok | E94: =SUM(F94:R94) -> 0 | P94: =$E$92/2 -> 0 | Q94: =$E$92/2 -> 0
D95: Bunga | P95: =($E$16/12)*1*P93 -> 0 | Q95: =($E$16/12)*1*Q93 -> 0
E97: 0
D98: OS | F98: =E99 -> 0 | G98: =F98-F99 -> 0 | H98: =G98-G99 -> 0 | I98: =H98-H99 -> 0 | J98: =I98-I99 -> 0 | K98: =J98-J99 -> 0 | L98: =K98-K99 -> 0 | M98: =L98-L99 -> 0 | N98: =M98-M99 -> 0 | ... Q98: =P98-P99 -> 0
D99: Pokok | E99: =SUM(F99:R99) -> 0 | F99: =$E$97/12 -> 0 | G99: =$E$97/12 -> 0 | H99: =$E$97/12 -> 0 | I99: =$E$97/12 -> 0 | J99: =$E$97/12 -> 0 | K99: =$E$97/12 -> 0 | L99: =$E$97/12 -> 0 | M99: =$E$97/12 -> 0 | ... Q99: =$E$97/12 -> 0
D100: Bunga | F100: =($E$16/12)*1*F98 -> 0 | G100: =($E$16/12)*1*G98 -> 0 | H100: =($E$16/12)*1*H98 -> 0 | I100: =($E$16/12)*1*I98 -> 0 | J100: =($E$16/12)*1*J98 -> 0 | K100: =($E$16/12)*1*K98 -> 0 | L100: =($E$16/12)*1*L98 -> 0 | M100: =($E$16/12)*1*M98 -> 0 | ... Q100: =($E$16/12)*1*Q98 -> 0
D102: TOTAL
D103: Pokok | E103: =SUM(F103:Q103) -> 971223 | F103: =F84+F89+F94+F99 -> 971223 | G103: =G84+G89+G94+G99 -> 0 | H103: =H84+H89+H94+H99 -> 0 | I103: =I84+I89+I94+I99 -> 0 | J103: =J84+J89+J94+J99 -> 0 | K103: =K84+K89+K94+K99 -> 0 | L103: =L84+L89+L94+L99 -> 0 | M103: =M84+M89+M94+M99 -> 0 | ... Q103: =Q84+Q89+Q94+Q99 -> 0
D104: Bunga | E104: =SUM(F104:Q104) -> 8813.8487 | F104: =F85+F90+F95+F100 -> 8813.8487 | G104: =G85+G90+G95+G100 -> 0 | H104: =H85+H90+H95+H100 -> 0 | I104: =I85+I90+I95+I100 -> 0 | J104: =J85+J90+J95+J100 -> 0 | K104: =K85+K90+K95+K100 -> 0 | L104: =L85+L90+L95+L100 -> 0 | M104: =M85+M90+M95+M100 -> 0 | ... Q104: =Q85+Q90+Q95+Q100 -> 0

Sheet Profitability 5 lokasi
C2: TABEL PROFITABILITY PROJECT | G2: KESIMPULAN ANALISIS KELAYAKAN PROJECT
C3: INFORMASI PROJECT | G3: =E6 -> Pekerjaan Pengadaan BBM Telkomsel 5 Lokasi
C4: Nama Pelanggan | E4: Telkomsel | G4: =E4 -> Telkomsel
C5: Kategori Project | E5: PS | G5: REVENUE | I5: =IF(E37=D55,E37,"perhitungan salah, CEK KEMBALI CASH FLOW DAN BLOCK REVENUE STREAM") -> 279594750 | J5: =I5=E37 -> TRUE
C6: Nama Project | E6: Pekerjaan Pengadaan BBM Telkomsel 5 Lokasi | G6: TOTAL BEBAN/CASH OUT | I6: =IF(E23=D58*-1,E23,"perhitungan salah, CEK KEMBALI CASH FLOW DAN BLOCKCOST STRUCTURE") -> 2.039678e+08 | J6: =I6=E23 -> TRUE
C7: Lokasi Project | E7: Telkomsel 5 Lokasi | G7: GROSS MARGIN | H7: =I7/I5 -> 0.27048774 | I7: =I5-I6 -> 75626951 | J7: =I7=D67 -> TRUE
C8: Estimasi mulai pekerjaan (MM/YY) | E8: 46259 | G8: Total Pajak PPH | I8: =E41 -> 7409260.9 | J8: =I8=E41 -> TRUE
A9: =IF(E9="",0,1) -> 1 | C9: Durasi Project (bulan) | E9: 1 | G9: GROSS MARGIN + PPH | H9: =I9/I5 -> 0.24398774 | I9: =I7-I8 -> 68217690 | J9: =I9=D73 -> TRUE
A10: =IF(E10="",0,1) -> 1 | C10: Durasi Retensi (bulan) | E10: 0 | G10: Provisi | I10: =D76*-1 -> 33654.687 | J10: =I10=E45 -> TRUE
C11: Pengawasan Konstruksi Sendiri / Menggunakan MK ? | E11: Sendiri ( by GSD ) | F11: *pilihan | G11: Bunga Pinjaman | I11: =D77*-1 -> 30541.628 | J11: =I11=E46 -> TRUE
C12: Tipe Bagunan | D12: {=IF(E37<='[128]Tabel PUPR'!A15,'[128]Tabel PUPR'!B15,IF(E37<='[128]Tabel PUPR'!A16,'[128]Tabel PUPR'!B16,IF(E37<='[128]Tabel PUPR'!A17,'[128]Tabel PUPR'!B17,IF(E37<='[128]Tabel PUPR'!A18,'[128]Tabel PUPR'!B18,IF(E37<='[128]Tabel PUPR'!A19,'[128]Tabel PUPR'!B19,IF(E37<='[128]Tabel PUPR'!A20,'[128]Tabel PUPR'!B20,IF(E37<='[128]Tabel PUPR'!A21,'[128]Tabel PUPR'!B21,IF(E37<='[128]Tabel PUPR'!A22,'[128]Tabel PUPR'!B22,IF(E37<='[128]Tabel PUPR'!A23,'[128]Tabel PUPR'!B23,IF(E37<='[128]Tabel PUPR'!A24,'[128]Tabel PUPR'!B24,IF(E37<='[128]Tabel PUPR'!A25,k,k)))))))))))} -> b | E12: Sederhana ( < 2 lantai) | F12: *pilihan | G12: NET INCOME | H12: =I12/I5 -> 0.24375813 | I12: =I9-SUM(I10:I11) -> 68153493 | J12: =I12=F79 -> TRUE
C13: TOP Pembayaran Kepada Mitra | E13: setelah BAST | G13: Kredit PPN | I13: =-D72 -> 8318964.6
C14: TOP Pembayaran Pelanggan | E14: setelah BAST | G14: NET CASH FLOW | H14: =IF(I14>0,"Cashflow Positif","Cashflow Negatif") -> Cashflow Positif | I14: =I12-I13 -> 59834529 | N14: CATATAN:
C15: ASUMSI-ASUMSI | G15: CF selama kontrak | H15: =COUNTIF(E79:Q79,"<"&0) -> 0 | I15: =IF(H15>0,"Terdapat CF Negatif","All CF Positif") -> All CF Positif
A16: =IF(E10=[129]key!A3,1,0) -> 0 | C16: Suku Bunga per tahun | E16: 0.1089 | G16: KESIMPULAN | H16: =IF(H12>0%,IF(H15=0,IF(H12>10.89%,"Layak dengan Net Income sebesar",IF(I5>1000000000,IF(H12>10.89%,"Tidak Layak dengan Net income dibawah treshold ",IF(H12>0%,"Tidak Layak dengan Net income dibawah treshold","Tidak Layak dengan Net income dibawah treshold")),"Tidak Layak dengan Net income dibawah treshold")),"Tidak Layak dengan Net Income sebesar"),"Tidak Layak dengan Net income dibawah treshold") -> Layak dengan Net Income sebesar | N16: * JIKA TERDAPAT CF NEGATIF :
C17: Suku Bunga per bulan | E17: =E16/12 -> 0.009075 | H17: =H12 -> 0.24375813 | N17: 1. adjust nilai pinjaman hingga CF positif
C18: Pemodalan: Loan | E18: 1 | G18: REVENUE INCL PPN | H18: 11/12*12% | I18: =I5+D70 -> 3.1035017e+08 | N18: 2. Adjust asumsi pembayaran mitra / customer, namun harus sesuai dengan
C19: Provisi | E19: 0.01 | G19: Notes lain-lain: | N19: kondisi aktual / konfirmasi dengan pihak OM
C20: PPN | E20: 0.12 | G20: =C24 -> Biaya Mitra Pelaksana (Exclude PPN) | I20: =E24 -> 2.039678e+08
C21: PPH pasal 23 | E21: 0.0265 | G21: =C31 -> BOP Project | I21: =E31 -> 0
C22: Periode Pinjaman (Bulan) | E22: =E9 -> 1 | G22: =C39 -> Management Fee GSD | I22: =E39 -> 75626951
C23: COST STRUCTURE / CASH OUT | E23: =SUM(E24:E31) -> 2.039678e+08
C24: Biaya Mitra Pelaksana (Exclude PPN) | E24: =+COGS!H12 -> 2.039678e+08
C25: BEBAN LAINNYA | E25: 0
C26: Fee Fasilitas Jaminan | F26: * Minimal 500rb dengan catatan apabila contohnya: 1. Nilai Proyek 10M 2. Jangka waktu kerjasama adalah 3 bulan 3. Nilai Jaminan Dipersyaratkan 15% Maka Cost untuk fee: =(((0.5%/12)x3)x(15%x10M)
C27: Admin Fasilitas Jaminan | F27: * Apabila ada jaminan, biaya admin Rp 250.000,-
C28: Construction Assurance Risk ( CAR) | E28: 0
C29: Iuran Jasa Konstruksi | E29: 0
C30: Biaya Pengawasan | D30: =IF(E11='[128]Tabel PUPR'!D4,0%,VLOOKUP([128]Profitability!D12,'[128]Tabel PUPR'!B15:E25,IF([128]Profitability!E12='[128]Tabel PUPR'!A8,2,IF([128]Profitability!D12='[128]Tabel PUPR'!A9,3,4)))) -> 0 | E30: =D30*$E$24 -> 0 | F30: Berdasarkan PUPR : | G30: 0
C31: BOP Project | D31: =G31 -> 0 | E31: =D31*$E$24 -> 0 | F31: Berdasarkan PUPR : | G31: 0 | H31: *% bisa disesuaikan dengan asumsi sendiri pada kolom D31
C32: JAMINAN - JAMINAN | E32: =SUM(E33:E36) -> 0
C33: Jaminan Uang muka | D33: 0 | E33: =D33*$E$37 -> 0 | F33: * cek dan sesuaikan pengenaan % terhadap revenue / isi nilai manual pada kolom E
C34: Jaminan Penawaran | D34: 0 | E34: =D34*$E$37 -> 0 | F34: * cek dan sesuaikan pengenaan % terhadap revenue / isi nilai manual pada kolom E
C35: Jaminan Pelaksanaan | D35: 0 | E35: =D35*$E$37 -> 0 | F35: * cek dan sesuaikan pengenaan % terhadap revenue / isi nilai manual pada kolom E
C36: Jaminan Pemeliharaan | D36: 0 | E36: =D36*$E$37 -> 0 | F36: * cek dan sesuaikan pengenaan % terhadap revenue / isi nilai manual pada kolom E
C37: REVENUE STREAM / CASH IN | E37: =SUM(E38:E39) -> 279594750 | G37: 279594750
C38: Jasa Pelaksanaan konstruksi | E38: =E24 -> 2.039678e+08
C39: Management Fee GSD | D39: 0.37077887 | E39: =D39*SUM(E38) -> 75626951 | F39: *terhadap nilai mitra
C40: PERPAJAKAN
C41: PPh | E41: =D68*-1 -> 7409260.9
C42: PPn | E42: =D72*-1 -> 8318964.6
C43: PINJAMAN
C44: Besar Pinjaman | E44: =D74 -> 3365468.7 | G44: Hendroyono | I44: Abimanyu | K44: Agung Wibowo
C45: Biaya Provisi | E45: =-D76 -> 33654.687 | G45: Mgr Planning & Delivery | I45: Mgr Marketing, Sales & Solution | K45: Mgr Business Support & Risk Management
C46: Bunga Pinjaman | E46: =D77*-1 -> 30541.628
C48: CASHFLOW PROJECT
C49: Jangka Waktu | D49: Total | E49: 0 | F49: 1 | G49: 2 | H49: 3 | I49: 4 | J49: 5 | K49: 6 | L49: 7 | M49: 8 | N49: 9 | O49: 10 | P49: 11 | Q49: 12
A50: 1 | C50: Bulan | E50: =E8 -> 46259 | F50: =EDATE(E50,1) -> 46290 | G50: =EDATE(F50,1) -> 46320 | H50: =EDATE(G50,1) -> 46351 | I50: =EDATE(H50,1) -> 46381 | J50: =EDATE(I50,1) -> 46412 | K50: =EDATE(J50,1) -> 46443 | L50: =EDATE(K50,1) -> 46471 | M50: =EDATE(L50,1) -> 46502 | ... Q50: =EDATE(P50,1) -> 46624
A51: =A50+1 -> 2 | C51: TOP (progress)
C52: % PROGRESS PEKERJAAN | D52: =MAX(E52:Q52) -> 1 | E52: 0 | F52: 1 | G52: =IF(G49<=$E$9,100%/$E$9*G49,0) -> 0 | H52: =IF(H49<=$E$9,100%/$E$9*H49,0) -> 0 | I52: =IF(I49<=$E$9,100%/$E$9*I49,0) -> 0 | J52: =IF(J49<=$E$9,100%/$E$9*J49,0) -> 0 | K52: =IF(K49<=$E$9,100%/$E$9*K49,0) -> 0 | L52: =IF(L49<=$E$9,100%/$E$9*L49,0) -> 0 | M52: =IF(M49<=$E$9,100%/$E$9*M49,0) -> 0 | N52: =IF(N49<=$E$9,100%/$E$9*N49,0) -> 0 | ... Q52: =IF(Q49<=$E$9,100%/$E$9*Q49,0) -> 0
C53: % TERM OF PAYMENT PELANGGAN | D53: =SUM(E53:Q53) -> 1 | E53: 0 | F53: 1 | J53: 0 | K53: 0 | L53: 0 | M53: 0 | N53: 0 | O53: 0 | P53: 0 | Q53: 0 | R53: * sesuaikan dengan TOP
C54: % TERM OF PAYMENT KEPADA MITRA | D54: =SUM(E54:Q54) -> 1 | E54: =E53 -> 0 | F54: =F53 -> 1 | G54: =G53 -> 0 | H54: =H53 -> 0 | I54: =I53 -> 0 | J54: =J53 -> 0 | K54: =K53 -> 0 | L54: =L53 -> 0 | ... Q54: =Q53 -> 0
A55: =#REF!+1 -> #REF! | C55: =C37 -> REVENUE STREAM / CASH IN | D55: =SUM(E55:Q55) -> 279594750 | E55: =SUM(E56:E57) -> 0 | F55: =SUM(F56:F57) -> 279594750 | G55: =SUM(G56:G57) -> 0 | H55: =SUM(H56:H57) -> 0 | I55: =SUM(I56:I57) -> 0 | J55: =SUM(J56:J57) -> 0 | K55: =SUM(K56:K57) -> 0 | L55: =SUM(L56:L57) -> 0 | ... Q55: =SUM(Q56:Q57) -> 0
A56: =A55+1 -> #REF! | C56: Jasa Pelaksanaan konstruksi | D56: =SUM(E56:Q56) -> 2.039678e+08 | E56: 0 | F56: =F53*$E$38 -> 2.039678e+08 | G56: =G53*$E$38 -> 0 | H56: =H53*$E$38 -> 0 | I56: =I53*$E$38 -> 0 | J56: =J53*$E$38 -> 0 | K56: =K53*$E$38 -> 0 | L56: =L53*$E$38 -> 0 | M56: =M53*$E$38 -> 0 | ... Q56: =Q53*$E$38 -> 0
C57: =C39 -> Management Fee GSD | D57: =SUM(E57:Q57) -> 75626951 | E57: 0 | F57: =$E$39*F53 -> 75626951 | G57: =$E$39*G53 -> 0 | H57: =$E$39*H53 -> 0 | I57: =$E$39*I53 -> 0 | J57: =$E$39*J53 -> 0 | K57: =$E$39*K53 -> 0 | L57: =$E$39*L53 -> 0 | M57: =$E$39*M53 -> 0 | ... Q57: =$E$39*Q53 -> 0
A58: =#REF!+1 -> #REF! | C58: =C23 -> COST STRUCTURE / CASH OUT | D58: =SUM(E58:Q58) -> -2.039678e+08 | E58: =SUM(E59:E66) -> 0 | F58: =SUM(F59:F66) -> -2.039678e+08 | G58: =SUM(G59:G66) -> 0 | H58: =SUM(H59:H66) -> 0 | I58: =SUM(I59:I66) -> 0 | J58: =SUM(J59:J66) -> 0 | K58: =SUM(K59:K66) -> 0 | L58: =SUM(L59:L66) -> 0 | ... Q58: =SUM(Q59:Q66) -> 0
A59: =#REF!+1 -> #REF! | C59: =C24 -> Biaya Mitra Pelaksana (Exclude PPN) | D59: =SUM(E59:Q59) -> -2.039678e+08 | E59: =-E54*$E$24 -> 0 | F59: =-F54*$E$24 -> -2.039678e+08 | G59: =-G54*$E$24 -> 0 | H59: =-H54*$E$24 -> 0 | I59: =-I54*$E$24 -> 0 | J59: =-J54*$E$24 -> 0 | K59: =-K54*$E$24 -> 0 | L59: =-L54*$E$24 -> 0 | ... Q59: =-Q54*$E$24 -> 0
C60: =C25 -> BEBAN LAINNYA | D60: =SUM(E60:Q60) -> 0 | E60: 0 | F60: 0 | G60: 0 | H60: 0 | I60: 0 | J60: 0 | K60: 0 | L60: 0 | M60: 0 | N60: 0 | O60: 0 | P60: 0 | Q60: 0
C61: =C26 -> Fee Fasilitas Jaminan | D61: =SUM(E61:Q61) -> 0 | E61: =-E26 -> 0
C62: =C27 -> Admin Fasilitas Jaminan | D62: =SUM(E62:Q62) -> 0 | E62: =-E27 -> 0
C63: =C28 -> Construction Assurance Risk ( CAR) | D63: =SUM(E63:Q63) -> 0 | E63: 0 | F63: 0 | G63: 0 | H63: 0 | I63: 0 | J63: 0 | K63: 0 | L63: 0 | M63: 0 | N63: 0 | O63: 0 | P63: 0 | Q63: 0
C64: =C29 -> Iuran Jasa Konstruksi | D64: =SUM(E64:Q64) -> 0 | E64: 0 | F64: 0 | G64: 0 | H64: 0 | I64: 0 | J64: 0 | K64: 0 | L64: 0 | M64: 0 | N64: 0 | O64: 0 | P64: 0 | Q64: 0
C65: =C30 -> Biaya Pengawasan | D65: =SUM(E65:Q65) -> 0 | E65: 0 | F65: =-$E$30/($E$9) -> 0 | G65: =-$E$30/($E$9) -> 0 | H65: =-$E$30/($E$9) -> 0 | I65: =-$E$30/($E$9) -> 0 | J65: =-$E$30/($E$9) -> 0 | K65: =-$E$30/($E$9) -> 0 | L65: =-$E$30/($E$9) -> 0 | M65: =-$E$30/($E$9) -> 0 | ... Q65: =-$E$30/($E$9) -> 0
C66: =C31 -> BOP Project | D66: =SUM(E66:Q66) -> 0 | F66: =-$E$31/($E$9) -> 0
A67: =#REF!+1 -> #REF! | C67: GROSS MARGIN / EBIT | D67: =SUM(E67:Q67) -> 75626951 | E67: =E55+E58 -> 0 | F67: =F55+F58 -> 75626951 | G67: =G55+G58 -> 0 | H67: =H55+H58 -> 0 | I67: =I55+I58 -> 0 | J67: =J55+J58 -> 0 | K67: =K55+K58 -> 0 | L67: =L55+L58 -> 0 | ... Q67: =Q55+Q58 -> 0
A68: =A67+1 -> #REF! | C68: Pengurangan pph 23 | D68: =SUM(E68:Q68) -> -7409260.9 | E68: =-$E$21*E55 -> 0 | F68: =-$E$21*F55 -> -7409260.9 | G68: =-$E$21*G55 -> 0 | H68: =-$E$21*H55 -> 0 | I68: =-$E$21*I55 -> 0 | J68: =-$E$21*J55 -> 0 | K68: =-$E$21*K55 -> 0 | L68: =-$E$21*L55 -> 0 | ... Q68: =-$E$21*Q55 -> 0
C69: PPn yang harus dibayarkan | D69: =SUM(E69:Q69) -> 0
C70: PPn Keluaran | D70: =SUM(E70:Q70) -> 30755422 | E70: =11/12*12%*E55 -> 0 | F70: =11/12*12%*F55 -> 30755422 | G70: =11/12*12%*G55 -> 0 | H70: =11/12*12%*H55 -> 0 | I70: =11/12*12%*I55 -> 0 | J70: =11/12*12%*J55 -> 0 | K70: =11/12*12%*K55 -> 0 | L70: =11/12*12%*L55 -> 0 | ... Q70: =11/12*12%*Q55 -> 0
C71: PPn Masukan | D71: =SUM(E71:Q71) -> -22436458 | E71: =11/12*12%*E59 -> 0 | F71: =11/12*12%*F59 -> -22436458 | G71: =11/12*12%*G59 -> 0 | H71: =11/12*12%*H59 -> 0 | I71: =11/12*12%*I59 -> 0 | J71: =11/12*12%*J59 -> 0 | K71: =11/12*12%*K59 -> 0 | L71: =11/12*12%*L59 -> 0 | ... Q71: =11/12*12%*Q59 -> 0
C72: Kredit PPn | D72: =SUM(E72:Q72) -> -8318964.6 | E72: =-(E70+E71) -> 0 | F72: =-(F70+F71) -> -8318964.6 | G72: =-(G70+G71) -> 0 | H72: =-(H70+H71) -> 0 | I72: =-(I70+I71) -> 0 | J72: =-(J70+J71) -> 0 | K72: =-(K70+K71) -> 0 | L72: =-(L70+L71) -> 0 | ... Q72: =-(Q70+Q71) -> 0
A73: =#REF!+1 -> #REF! | C73: =G9 -> GROSS MARGIN + PPH | D73: =SUM(E73:Q73) -> 68217690 | E73: =SUM(E67:E68) -> 0 | F73: =SUM(F67:F68) -> 68217690 | G73: =SUM(G67:G68) -> 0 | H73: =SUM(H67:H68) -> 0 | I73: =SUM(I67:I68) -> 0 | J73: =SUM(J67:J68) -> 0 | K73: =SUM(K67:K68) -> 0 | L73: =SUM(L67:L68) -> 0 | ... Q73: =SUM(Q67:Q68) -> 0
C74: Penarikan Pinjaman | D74: =SUM(E74:Q74) -> 3365468.7 | E74: =E82 -> 3365468.7
C75: Pembayaran Pokok | D75: =SUM(E75:Q75) -> -3365468.7 | F75: =-F103 -> -3365468.7 | G75: =-G103 -> 0 | H75: =-H103 -> 0 | I75: =-I103 -> 0 | J75: =-J103 -> 0 | K75: =-K103 -> 0 | L75: =-L103 -> 0 | M75: =-M103 -> 0 | ... Q75: =-Q103 -> 0
A76: =A68+1 -> #REF! | C76: Biaya Provisi | D76: =SUM(E76:Q76) -> -33654.687 | E76: =-E74*1% -> -33654.687 | F76: =-F74*1% -> 0 | G76: =-G74*1% -> 0 | H76: =-H74*1% -> 0 | I76: =-I74*1% -> 0 | J76: =-J74*1% -> 0 | K76: =-K74*1% -> 0 | L76: =-L74*1% -> 0 | ... Q76: =-Q74*1% -> 0
A77: =A76+1 -> #REF! | C77: Beban Bunga | D77: =SUM(E77:Q77) -> -30541.628 | F77: =-$F$104 -> -30541.628 | G77: =-G104 -> 0 | H77: =-H104 -> 0 | I77: =-I104 -> 0 | J77: =-J104 -> 0 | K77: =-K104 -> 0 | L77: =-L104 -> 0 | M77: =-M104 -> 0 | N77: =-N104 -> 0 | ... Q77: =-Q104 -> 0
A78: =A77+1 -> #REF! | C78: CASH MARGIN | D78: =SUM(E78:Q78) -> 68153493 | E78: =E73+SUM(E74:E77) -> 3331814 | F78: =F73+SUM(F74:F77) -> 64821679 | G78: =G73+SUM(G74:G77) -> 0 | H78: =H73+SUM(H74:H77) -> 0 | I78: =I73+SUM(I74:I77) -> 0 | J78: =J73+SUM(J74:J77) -> 0 | K78: =K73+SUM(K74:K77) -> 0 | L78: =L73+SUM(L74:L77) -> 0 | ... Q78: =Q73+SUM(Q74:Q77) -> 0
A79: =A78+1 -> #REF! | C79: CASH FLOW | E79: =E78+D79 -> 3331814 | F79: =F78+E79 -> 68153493
G80: =F79=D78 -> TRUE
F81: =1.65% -> 0.0165
E82: =F81*E24 -> 3365468.7
D83: OS | F83: =E84 -> 3365468.7 | H83: =G83-G84 -> 0 | I83: =H83-H84 -> 0 | J83: =I83-I84 -> 0 | K83: =J83-J84 -> 0 | L83: =K83-K84 -> 0 | M83: =L83-L84 -> 0 | N83: =M83-M84 -> 0 | O83: =N83-N84 -> 0 | ... Q83: =P83-P84 -> 0
D84: Pokok | E84: =SUM(F84:R84) -> 3365468.7 | F84: =$E$82/1 -> 3365468.7
D85: Bunga | F85: =($E$16/12)*1*F83 -> 30541.628 | H85: =($E$16/12)*1*H83 -> 0 | I85: =($E$16/12)*1*I83 -> 0 | J85: =($E$16/12)*1*J83 -> 0 | K85: =($E$16/12)*1*K83 -> 0 | L85: =($E$16/12)*1*L83 -> 0 | M85: =($E$16/12)*1*M83 -> 0 | N85: =($E$16/12)*1*N83 -> 0 | O85: =($E$16/12)*1*O83 -> 0 | ... Q85: =($E$16/12)*1*Q83 -> 0
E87: 0
D88: OS | M88: =E89 -> 0 | N88: =M88-M89 -> 0 | O88: =N88-N89 -> 0 | P88: =O88-O89 -> 0 | Q88: =P88-P89 -> 0
D89: Pokok | E89: =SUM(F89:R89) -> 0 | M89: =E87/5 -> 0 | N89: =F87/5 -> 0 | O89: =G87/5 -> 0 | P89: =H87/5 -> 0 | Q89: =I87/5 -> 0
D90: Bunga | M90: =($E$16/12)*1*M88 -> 0 | N90: =($E$16/12)*1*N88 -> 0 | O90: =($E$16/12)*1*O88 -> 0 | P90: =($E$16/12)*1*P88 -> 0 | Q90: =($E$16/12)*1*Q88 -> 0
E92: 0
D93: OS | P93: =E92 -> 0 | Q93: =P93-P94 -> 0
D94: Pokok | E94: =SUM(F94:R94) -> 0 | P94: =$E$92/2 -> 0 | Q94: =$E$92/2 -> 0
D95: Bunga | P95: =($E$16/12)*1*P93 -> 0 | Q95: =($E$16/12)*1*Q93 -> 0
E97: 0
D98: OS | F98: =E99 -> 0 | G98: =F98-F99 -> 0 | H98: =G98-G99 -> 0 | I98: =H98-H99 -> 0 | J98: =I98-I99 -> 0 | K98: =J98-J99 -> 0 | L98: =K98-K99 -> 0 | M98: =L98-L99 -> 0 | N98: =M98-M99 -> 0 | ... Q98: =P98-P99 -> 0
D99: Pokok | E99: =SUM(F99:R99) -> 0 | F99: =$E$97/12 -> 0 | G99: =$E$97/12 -> 0 | H99: =$E$97/12 -> 0 | I99: =$E$97/12 -> 0 | J99: =$E$97/12 -> 0 | K99: =$E$97/12 -> 0 | L99: =$E$97/12 -> 0 | M99: =$E$97/12 -> 0 | ... Q99: =$E$97/12 -> 0
D100: Bunga | F100: =($E$16/12)*1*F98 -> 0 | G100: =($E$16/12)*1*G98 -> 0 | H100: =($E$16/12)*1*H98 -> 0 | I100: =($E$16/12)*1*I98 -> 0 | J100: =($E$16/12)*1*J98 -> 0 | K100: =($E$16/12)*1*K98 -> 0 | L100: =($E$16/12)*1*L98 -> 0 | M100: =($E$16/12)*1*M98 -> 0 | ... Q100: =($E$16/12)*1*Q98 -> 0
D102: TOTAL
D103: Pokok | E103: =SUM(F103:Q103) -> 3365468.7 | F103: =F84+F89+F94+F99 -> 3365468.7 | G103: =G84+G89+G94+G99 -> 0 | H103: =H84+H89+H94+H99 -> 0 | I103: =I84+I89+I94+I99 -> 0 | J103: =J84+J89+J94+J99 -> 0 | K103: =K84+K89+K94+K99 -> 0 | L103: =L84+L89+L94+L99 -> 0 | M103: =M84+M89+M94+M99 -> 0 | ... Q103: =Q84+Q89+Q94+Q99 -> 0
D104: Bunga | E104: =SUM(F104:Q104) -> 30541.628 | F104: =F85+F90+F95+F100 -> 30541.628 | G104: =G85+G90+G95+G100 -> 0 | H104: =H85+H90+H95+H100 -> 0 | I104: =I85+I90+I95+I100 -> 0 | J104: =J85+J90+J95+J100 -> 0 | K104: =K85+K90+K95+K100 -> 0 | L104: =L85+L90+L95+L100 -> 0 | M104: =M85+M90+M95+M100 -> 0 | ... Q104: =Q85+Q90+Q95+Q100 -> 0

Sheet COGS
B2: RINCIAN KEBUTUHAN BBM TELKOMSEL 5 LOKASI | P2: Budget Telkomsel
F3: BEBAN | I3: BUDGET TELKOMSEL
B4: NO | C4: LOKASI | D4: SATUAN | E4: QTY | F4: HARGA | G4: HUMLAH | H4: TOTAL | I4: BBM/ LTR | J4: FEE BBM/ LTR | K4: PBBKB 7.5% | L4: SUB TOTAL/ LTR | M4: TOTAL/ LOKASI | N4: Margin Gross
B6: 1 | C6: STO Maumere | D6: Liter | E6: 1500 | F6: 21982 | G6: =F6*E6 -> 32973000 | H6: =G6 -> 32973000 | I6: 26000 | J6: 1500 | K6: 1931 | L6: =I6+J6+K6 -> 29431 | M6: =E6*L6 -> 44146500 | N6: =M6-H6 -> 11173500
B7: =B6+1 -> 2 | C7: HR Muhammad | D7: Liter | E7: 1000 | F7: =25000/1.11 -> 22522.523 | G7: =F7*E7 -> 22522523 | H7: =G7 -> 22522523 | I7: 26000 | J7: 1500 | K7: 1931 | L7: =I7+J7+K7 -> 29431 | M7: =E7*L7 -> 29431000 | N7: =M7-H7 -> 6908477.5
B8: =B7+1 -> 3 | C8: TTC Gayungan | D8: Liter | E8: 4000 | F8: =F7 -> 22522.523 | G8: =F8*E8 -> 90090090 | H8: =G8 -> 90090090 | I8: 26000 | J8: 1500 | K8: 1931 | L8: =I8+J8+K8 -> 29431 | M8: =E8*L8 -> 117724000 | N8: =M8-H8 -> 27633910
B9: =B8+1 -> 4 | C9: STO Palapa Kupang | D9: Liter | E9: 1000.0085 | F9: =F6 -> 21982 | G9: =F9*E9 -> 21982187 | H9: =G9 -> 21982187 | I9: 26000 | J9: 1500 | K9: 1931 | L9: =I9+J9+K9 -> 29431 | M9: =E9*L9 -> 29431250 | N9: =M9-H9 -> 7449063.3
B10: =B9+1 -> 5 | C10: TTC Gombel | D10: Liter | E10: 2000 | F10: 18200 | G10: =F10*E10 -> 36400000 | H10: =G10 -> 36400000 | I10: 26000 | J10: 1500 | K10: 1931 | L10: =I10+J10+K10 -> 29431 | M10: =E10*L10 -> 58862000 | N10: =M10-H10 -> 22462000
C12: TOTAL | H12: =SUM(H6:H11) -> 2.039678e+08 | M12: =SUM(M6:M11) -> 279594750 | N12: =SUM(N6:N11) -> 75626951
L13: margin | M13: =M12-H12 -> 75626951
L14: % | M14: =M13/H12 -> 0.37077887
M16: 0.37077887
P20: BBM NUSRA | R20: 19 Agustus 2026
P64: BBM SURABAYA
P97: BBM GOMBEL | R97: 20 Agustus 2026

Sheet Tabel PUPR
A1: Suplier back to back | D1: Pengawasan Project
A3: YA | D3: Menggunakan MK
A4: TIDAK | D4: Sendiri ( by GSD )
A6: Tipe Bagunan
A8: Sederhana ( < 2 lantai)
A9: Tidak Sederhana (> 2 lantai)
A10: Kriteria Khusus ( Daerah sulit / neocentrix)
A12: Pengawasan
A13: Nilai project | C13: Sederhana | D13: Tidak Sederhana | E13: Klasifikasi Khusus
A14: kecil sama dari
A15: 250000000 | B15: a | C15: 0.1059 | D15: 0.2108 | E15: 0.1574
A16: 500000000 | B16: b | C16: 0.0915 | D16: 0.182 | E16: 0.1323
A17: 1000000000 | B17: c | C17: 0.0772 | D17: 0.1537 | E17: 0.1129
A18: 2500000000 | B18: d | C18: 0.0647 | D18: 0.1288 | E18: 0.0964
A19: 5000000000 | B19: e | C19: 0.0541 | D19: 0.1076 | E19: 0.0871
A20: 10000000000 | B20: f | C20: 0.0449 | D20: 0.0762 | E20: 0.0756
A21: 25000000000 | B21: g | C21: 0.0403 | D21: 0.0513 | E21: 0.0682
A22: 50000000000 | B22: h | C22: 0.0363 | D22: 0.035 | E22: 0.046
A23: 100000000000 | B23: i | C23: 0.0248 | D23: 0.0239 | E23: 0.0314
A24: 250000000000 | B24: j | C24: 0.0159 | D24: 0.015 | E24: 0.029
A25: 500000000000 | B25: k | C25: 0.0149 | D25: 0.011 | E25: 0.0273
A28: BOP (Pengelolaan Kegiatan)
A29: Nilai project | C29: Sederhana | D29: Tidak Sederhana | E29: Klasifikasi Khusus
A30: kecil sama dari
A31: 250000000 | B31: a | C31: 0.14 | D31: 0.16 | E31: 0.16
A32: 500000000 | B32: b | C32: 0.1 | D32: 0.1125 | E32: 0.1125
A33: 1000000000 | B33: c | C33: 0.0675 | D33: 0.0775 | E33: 0.0775
A34: 2500000000 | B34: d | C34: 0.042 | D34: 0.051 | E34: 0.051
A35: 5000000000 | B35: e | C35: 0.0285 | D35: 0.0336 | E35: 0.0335
A36: 10000000000 | B36: f | C36: 0.019 | D36: 0.0224 | E36: 0.0222
A37: 25000000000 | B37: g | C37: 0.012 | D37: 0.0142 | E37: 0.0142
A38: 50000000000 | B38: h | C38: 0.008 | D38: 0.0095 | E38: 0.0095
A39: 100000000000 | B39: i | C39: 0.0054 | D39: 0.0064 | E39: 0.0064
A40: 250000000000 | B40: j | C40: 0.0036 | D40: 0.004 | E40: 0.0041
A41: 500000000000 | B41: k | C41: 0.0025 | D41: 0.0028 | E41: 0.0028

Sheet SPH
B2: RINCIAN LAMPIRAN HARGA BBM TELKOMSEL | G2: 1.2 | Q2: Budget Telkomsel
G3: BEBAN | J3: REVENUE
B4: NO | C4: LOKASI | D4: SATUAN | E4: QTY | F4: HARGA | G4: HARGA | H4: SUBTOTAL | I4: TOTAL | J4: BBM/ LTR | K4: FEE BBM/ LTR | L4: PBBKB 7.5% | M4: SUB TOTAL/ LTR | N4: TOTAL/ LOKASI | O4: Margin Gross
B6: 1 | C6: STO Maumere | D6: Liter | E6: 1500 | F6: 21982 | G6: =G2*M6 -> 35317.2 | H6: =G6*E6 -> 52975800 | I6: =H6 -> 52975800 | J6: 26000 | K6: 1500 | L6: 1931 | M6: =J6+K6+L6 -> 29431 | N6: =E6*M6 -> 44146500 | O6: =N6-I6 -> -8829300
B7: =B6+1 -> 2 | C7: HR Muhammad | D7: Liter | E7: 1000 | F7: =25000/1.11 -> 22522.523 | G7: =G6 -> 35317.2 | H7: =G7*E7 -> 35317200 | I7: =H7 -> 35317200 | J7: 26000 | K7: 1500 | L7: 1931 | M7: =J7+K7+L7 -> 29431 | N7: =E7*M7 -> 29431000 | O7: =N7-I7 -> -5886200
B8: =B7+1 -> 3 | C8: TTC Gayungan | D8: Liter | E8: 4000 | F8: =F7 -> 22522.523 | G8: =G7 -> 35317.2 | H8: =G8*E8 -> 141268800 | I8: =H8 -> 141268800 | J8: 26000 | K8: 1500 | L8: 1931 | M8: =J8+K8+L8 -> 29431 | N8: =E8*M8 -> 117724000 | O8: =N8-I8 -> -23544800
B9: =B8+1 -> 4 | C9: STO Palapa Kupang | D9: Liter | E9: 1000.0085 | F9: =F6 -> 21982 | G9: =G8 -> 35317.2 | H9: =G9*E9 -> 35317500 | I9: =H9 -> 35317500 | J9: 26000 | K9: 1500 | L9: 1931 | M9: =J9+K9+L9 -> 29431 | N9: =E9*M9 -> 29431250 | O9: =N9-I9 -> -5886250
B10: =B9+1 -> 5 | C10: TTC Gombel | D10: Liter | E10: 2000 | F10: 18200 | G10: =G9 -> 35317.2 | H10: =G10*E10 -> 70634400 | I10: =H10 -> 70634400 | J10: 26000 | K10: 1500 | L10: 1931 | M10: =J10+K10+L10 -> 29431 | N10: =E10*M10 -> 58862000 | O10: =N10-I10 -> -11772400
C12: TOTAL | H12: =SUM(H6:H11) -> 335513700 | I12: =SUM(I6:I11) -> 335513700 | N12: =SUM(N6:N11) -> 279594750 | O12: =SUM(O6:O11) -> -55918950
M13: margin | N13: =N12-I12 -> -55918950
M14: % | N14: =N13/I12 -> -0.16666667
N16: 0.37077887
Q20: BBM NUSRA | S20: 19 Agustus 2026
G27: Simulasi perhitungan penawaran mitra
H28: DPP | I28: PBBKB | J28: Biaya Ongkir | K28: Total
G29: Telkomsel | H29: 26000 | I29: =H29*7.5% -> 1950 | J29: 1500 | K29: =SUM(H29:J29) -> 29450
G30: Nusra | H30: 28000 | I30: =H30*7.5% -> 2100 | J30: 1000 | K30: =SUM(H30:J30) -> 31100
G31: Jateng-Jatim | H31: 27600 | I31: =H31*7.5% -> 2070 | J31: 500 | K31: =SUM(H31:J31) -> 30170
G32: SPH | H32: 35317 | K32: =SUM(H32:J32) -> 35317
G36: Harga DPP | H36: 27600
G37: *) Harga belum termasuk Pajak PBBKB, Biaya Ongkir dan Pajak-pajak yang berlaku
Q64: BBM SURABAYA
Q97: BBM GOMBEL | S97: 20 Agustus 2026
